Workbook
Name CONSTR_MONTHS: Assumptions!$C$4
Name RETAIL_OPEN_M: Assumptions!$C$5
Name HOTEL_OPEN_M: Assumptions!$C$6
Name FIRST_CLOSING_M: Assumptions!$C$7
Name CLOSINGS_SPAN_M: Assumptions!$C$8
Name PERM_CONV_M: Assumptions!$C$9
Name EXIT_M: Assumptions!$C$10
Name UNITS_STUDIO: Assumptions!$C$13
Name SQFT_STUDIO: Assumptions!$C$14
Name PPSF_STUDIO: Assumptions!$C$15
Name UNITS_1BR: Assumptions!$C$16
Name SQFT_1BR: Assumptions!$C$17
Name PPSF_1BR: Assumptions!$C$18
Name UNITS_2BR: Assumptions!$C$19
Name SQFT_2BR: Assumptions!$C$20
Name PPSF_2BR: Assumptions!$C$21
Name UNITS_3BR: Assumptions!$C$22
Name SQFT_3BR: Assumptions!$C$23
Name PPSF_3BR: Assumptions!$C$24
Name UNITS_PH: Assumptions!$C$25
Name SQFT_PH: Assumptions!$C$26
Name PPSF_PH: Assumptions!$C$27
Name PARKING_SPACES: Assumptions!$C$28
Name PARKING_PRICE: Assumptions!$C$29
Name STORAGE_UNITS: Assumptions!$C$30
Name STORAGE_PRICE: Assumptions!$C$31
Name CLOSING_COST_PCT: Assumptions!$C$32
Name MARKETING_PCT: Assumptions!$C$33
Name LAND_COST: Assumptions!$C$36
Name ACQ_COST_PCT: Assumptions!$C$37
Name RES_GSF: Assumptions!$C$38
Name HOTEL_GSF: Assumptions!$C$39
Name RETAIL_GSF: Assumptions!$C$40
Name HC_PSF_RES: Assumptions!$C$41
Name HC_PSF_HOTEL: Assumptions!$C$42
Name HC_PSF_RETAIL: Assumptions!$C$43
Name CONTINGENCY_PCT: Assumptions!$C$44
Name SOFTCOST_PCT: Assumptions!$C$45
Name HOTEL_KEYS: Assumptions!$C$46
Name FFE_PER_KEY: Assumptions!$C$47
Name FFE_PSF_RETAIL: Assumptions!$C$48
Name DEVFEE_PCT: Assumptions!$C$49
Name LTC_PCT: Assumptions!$C$52
Name CT_SPREAD_PCT: Assumptions!$C$53
Name SOFR_FLOOR_PCT: Assumptions!$C$54
Name AVG_DRAWN_FRAC: Assumptions!$C$55
Name CT_COSTS_PCT: Assumptions!$C$56
Name PERM_LTV: Assumptions!$C$59
Name PERM_DSCR: Assumptions!$C$60
Name PERM_DY: Assumptions!$C$61
Name PERM_RATE_PCT: Assumptions!$C$62
Name PERM_AMORT_YRS: Assumptions!$C$63
Name PERM_COSTS_PCT: Assumptions!$C$64
Name ADR_Y1: Assumptions!$C$67
Name ADR_GROWTH_PCT: Assumptions!$C$68
Name OCC_Y1: Assumptions!$C$69
Name OCC_Y2: Assumptions!$C$70
Name OCC_STAB: Assumptions!$C$71
Name FB_REV_PCT: Assumptions!$C$72
Name OTHER_REV_PCT: Assumptions!$C$73

Sheet Cover
A1: Elite Luxury Mixed-Use Development Model
A3: ILLUSTRATIVE TEMPLATE — NOT A LIVE DEAL, NOT AN OFFERING, NOT INVESTMENT ADVICE. The SOFR forward curve is a placeholder assumption, not a live Chatham quote; paste live forwards into the SOFR sheet. All figures are illustrative defaults.
A5: Sheets
A6: Cover | B6: formula
A7: Assumptions | B7: input
A8: SOFR | B8: input
A9: SourcesUses | B9: formula
A10: SpendCurve | B10: formula
A11: CondoSellout | B11: formula
A12: RetailProForma | B12: formula
A13: HotelProForma | B13: formula
A14: ConstructionDebt | B14: formula
A15: PermanentDebt | B15: formula
A16: HotelValuation | B16: formula
A17: RetailValuation | B17: formula
... A21: Checks | B21: formula
A23: Blue font marks an input. Every other amount is an Excel formula.
A24: Condo economics are sellout revenue net of costs. No cap rate is applied to condos.
A25: XIRR on Returns is an output. It is not a waterfall distribution trigger.

Sheet Assumptions
A1: Assumptions
A2: Name | B2: Unit | C2: Value | D2: Note
A3: Timeline
A4: CONSTR_MONTHS | B4: months | C4: 30 | D4: Construction duration, months 1 through this month
A5: RETAIL_OPEN_M | B5: month | C5: 29 | D5: First month of retail operations
A6: HOTEL_OPEN_M | B6: month | C6: 31 | D6: First month of hotel operations
A7: FIRST_CLOSING_M | B7: month | C7: 33 | D7: First condo closing month
A8: CLOSINGS_SPAN_M | B8: months | C8: 36 | D8: Sellout length; last closing is first + span - 1
A9: PERM_CONV_M | B9: month | C9: 72 | D9: Permanent loan conversion month
A10: EXIT_M | B10: month | C10: 84 | D10: Terminal sale month; fixed at the last model column
A12: Condo program
A13: UNITS_STUDIO | B13: units | C13: 36 | D13: Studio inventory
A14: SQFT_STUDIO | B14: SF | C14: 650 | D14: Studio average size
A15: PPSF_STUDIO | B15: $/SF | C15: 1600 | D15: Studio contract price
A16: UNITS_1BR | B16: units | C16: 72 | D16: One-bedroom inventory
A17: SQFT_1BR | B17: SF | C17: 950 | D17: One-bedroom average size
A18: PPSF_1BR | B18: $/SF | C18: 1750 | D18: One-bedroom contract price
A19: UNITS_2BR | B19: units | C19: 54 | D19: Two-bedroom inventory
A20: SQFT_2BR | B20: SF | C20: 1450 | D20: Two-bedroom average size
A21: PPSF_2BR | B21: $/SF | C21: 1900 | D21: Two-bedroom contract price
A22: UNITS_3BR | B22: units | C22: 14 | D22: Three-bedroom inventory
A23: SQFT_3BR | B23: SF | C23: 2100 | D23: Three-bedroom average size
A24: PPSF_3BR | B24: $/SF | C24: 2200 | D24: Three-bedroom contract price
... A33: MARKETING_PCT | B33: % of gross | C33: 0.015 | D33: Marketing cost rate
A35: Development budget
A36: LAND_COST | B36: $ | C36: 85000000 | D36: Land, funded at month 1
A37: ACQ_COST_PCT | B37: % of land | C37: 0.01 | D37: Acquisition costs
A38: RES_GSF | B38: SF | C38: 240000 | D38: Residential gross area
A39: HOTEL_GSF | B39: SF | C39: 150000 | D39: Hotel gross area
A40: RETAIL_GSF | B40: SF | C40: 25000 | D40: Retail gross area
A41: HC_PSF_RES | B41: $/SF | C41: 700 | D41: Residential hard-cost unit rate
A42: HC_PSF_HOTEL | B42: $/SF | C42: 850 | D42: Hotel hard-cost unit rate
A43: HC_PSF_RETAIL | B43: $/SF | C43: 600 | D43: Retail hard-cost unit rate
A44: CONTINGENCY_PCT | B44: % of hard | C44: 0.04 | D44: Contingency
A45: SOFTCOST_PCT | B45: % of hard | C45: 0.12 | D45: Soft costs
A46: HOTEL_KEYS | B46: keys | C46: 200 | D46: Hotel keys
A47: FFE_PER_KEY | B47: $/key | C47: 45000 | D47: Hotel FF&E
... A49: DEVFEE_PCT | B49: % of fee base | C49: 0.04 | D49: Fee base is land, acquisition, hard, contingency, soft, and FF&E
A51: Construction debt
A52: LTC_PCT | B52: % of uses | C52: 0.6 | D52: Loan-to-cost, including the interest reserve
A53: CT_SPREAD_PCT | B53: annual | C53: 0.0275 | D53: Spread over SOFR
A54: SOFR_FLOOR_PCT | B54: annual | C54: 0 | D54: SOFR floor
A55: AVG_DRAWN_FRAC | B55: fraction | C55: 0.55 | D55: Average drawn fraction used only to size the interest reserve
A56: CT_COSTS_PCT | B56: % of commitment | C56: 0.0075 | D56: Construction loan closing costs
A58: Permanent debt
A59: PERM_LTV | B59: LTV cap | C59: 0.55 | D59: Cap on hotel plus retail value at conversion
A60: PERM_DSCR | B60: x | C60: 1.4 | D60: DSCR cap on T12 NOI at conversion
A61: PERM_DY | B61: debt yield | C61: 0.09 | D61: Debt-yield cap on T12 NOI at conversion
A62: PERM_RATE_PCT | B62: annual | C62: 0.0575 | D62: Fixed rate from conversion
A63: PERM_AMORT_YRS | B63: years | C63: 30 | D63: Amortization term
A64: PERM_COSTS_PCT | B64: % of proceeds | C64: 0.005 | D64: Permanent financing costs, at conversion, not in construction uses
A66: Hotel operations
A67: ADR_Y1 | B67: $ | C67: 650 | D67: Year-1 ADR
A68: ADR_GROWTH_PCT | B68: per year | C68: 0.025 | D68: ADR growth by operating year
A69: OCC_Y1 | B69: occupancy | C69: 0.65 | D69: Operating year 1
A70: OCC_Y2 | B70: occupancy | C70: 0.75 | D70: Operating year 2
A71: OCC_STAB | B71: occupancy | C71: 0.82 | D71: Operating year 3 and after
A72: FB_REV_PCT | B72: % of rooms | C72: 0.35 | D72: Food and beverage revenue
A73: OTHER_REV_PCT | B73: % of rooms | C73: 0.08 | D73: Other revenue
A74: HOTEL_UNDIST_PCT | B74: % of revenue | C74: 0.22 | D74: Undistributed expenses
A75: HOTEL_MGMT_PCT | B75: % of revenue | C75: 0.03 | D75: Management fee
A76: REPL_RESERVE_PCT | B76: % of revenue | C76: 0.035 | D76: Replacement reserve
A77: HOTEL_CAP | B77: cap rate | C77: 0.0725 | D77: Stabilization and exit cap rate
A79: Retail operations
A80: RETAIL_BASE_PSF | B80: $/SF | C80: 120 | D80: Year-1 base rent
A81: RETAIL_ESC_PCT | B81: per year | C81: 0.03 | D81: Annual escalation from retail open
A82: RETAIL_RECOV_PSF | B82: $/SF | C82: 18 | D82: Recoverable pool
A83: RETAIL_RECOV_RATIO | B83: ratio | C83: 0.9 | D83: Recovery ratio
A84: RETAIL_VAC_PCT | B84: % of base+recoveries | C84: 0.05 | D84: Vacancy and credit loss
A85: RETAIL_OP_PSF | B85: $/SF | C85: 9 | D85: Non-recoverable opex, not escalated
A86: RETAIL_MGMT_PCT | B86: % of EGI | C86: 0.02 | D86: Management fee
A87: RETAIL_CAP | B87: cap rate | C87: 0.0625 | D87: Stabilization and exit cap rate
A89: Exit and capital
A90: SELL_COST_PCT | B90: % of value | C90: 0.015 | D90: Cost of sale on hotel plus retail terminal value
A91: GP_EQUITY_PCT | B91: % of equity | C91: 0.1 | D91: GP co-invest share
A92: PREF_PCT | B92: annual | C92: 0.08 | D92: LP preferred return, monthly compounding
A93: CATCHUP_PCT | B93: % of profits | C93: 0.2 | D93: GP catch-up target
A94: T3_ACCRUAL_PCT | B94: annual | C94: 0.15 | D94: Tier-3 accrual gate, not an XIRR gate
A95: T3_LP_SPLIT | B95: LP share | C95: 0.7 | D95: LP share in tier 3
A96: T4_LP_SPLIT | B96: LP share | C96: 0.8 | D96: LP share in tier 4

Sheet SOFR
A1: SOFR
A2: =ROW()-1 | B2: =EOMONTH(DATE(2026,1,1),A2-1) | C2: 0.043 | D2: ASSUMPTION — placeholder forward; not a live Chatham quote. Paste Chatham forwards here. | E2: Paste target. Placeholder path is 4.30% at month 1 gliding linearly to 3.60% at month 24, then flat. Not a live quote.
A3: =ROW()-1 | B3: =EOMONTH(DATE(2026,1,1),A3-1) | C3: 0.042695652 | D3: ASSUMPTION — placeholder forward; not a live Chatham quote. Paste Chatham forwards here.
A4: =ROW()-1 | B4: =EOMONTH(DATE(2026,1,1),A4-1) | C4: 0.042391304 | D4: ASSUMPTION — placeholder forward; not a live Chatham quote. Paste Chatham forwards here.
A5: =ROW()-1 | B5: =EOMONTH(DATE(2026,1,1),A5-1) | C5: 0.042086957 | D5: ASSUMPTION — placeholder forward; not a live Chatham quote. Paste Chatham forwards here.
A6: =ROW()-1 | B6: =EOMONTH(DATE(2026,1,1),A6-1) | C6: 0.041782609 | D6: ASSUMPTION — placeholder forward; not a live Chatham quote. Paste Chatham forwards here.
A7: =ROW()-1 | B7: =EOMONTH(DATE(2026,1,1),A7-1) | C7: 0.041478261 | D7: ASSUMPTION — placeholder forward; not a live Chatham quote. Paste Chatham forwards here.
A8: =ROW()-1 | B8: =EOMONTH(DATE(2026,1,1),A8-1) | C8: 0.041173913 | D8: ASSUMPTION — placeholder forward; not a live Chatham quote. Paste Chatham forwards here.
A9: =ROW()-1 | B9: =EOMONTH(DATE(2026,1,1),A9-1) | C9: 0.040869565 | D9: ASSUMPTION — placeholder forward; not a live Chatham quote. Paste Chatham forwards here.
A10: =ROW()-1 | B10: =EOMONTH(DATE(2026,1,1),A10-1) | C10: 0.040565217 | D10: ASSUMPTION — placeholder forward; not a live Chatham quote. Paste Chatham forwards here.
A11: =ROW()-1 | B11: =EOMONTH(DATE(2026,1,1),A11-1) | C11: 0.04026087 | D11: ASSUMPTION — placeholder forward; not a live Chatham quote. Paste Chatham forwards here.
A12: =ROW()-1 | B12: =EOMONTH(DATE(2026,1,1),A12-1) | C12: 0.039956522 | D12: ASSUMPTION — placeholder forward; not a live Chatham quote. Paste Chatham forwards here.
A13: =ROW()-1 | B13: =EOMONTH(DATE(2026,1,1),A13-1) | C13: 0.039652174 | D13: ASSUMPTION — placeholder forward; not a live Chatham quote. Paste Chatham forwards here.
A14: =ROW()-1 | B14: =EOMONTH(DATE(2026,1,1),A14-1) | C14: 0.039347826 | D14: ASSUMPTION — placeholder forward; not a live Chatham quote. Paste Chatham forwards here.
... A85: =ROW()-1 | B85: =EOMONTH(DATE(2026,1,1),A85-1) | C85: 0.036 | D85: ASSUMPTION — placeholder forward; not a live Chatham quote. Paste Chatham forwards here.

Sheet SourcesUses
A1: SourcesUses
A2: Line | B2: Unit | C2: Amount | D2: Definition
A4: Land | B4: $ | C4: =LAND_COST | D4: Named input
A5: Acquisition costs | B5: $ | C5: =LAND_COST*ACQ_COST_PCT | D5: Land times acquisition rate
A6: Land and acquisition | B6: $ | C6: =C4+C5 | D6: Funded at month 1
A7: Hard costs residential | B7: $ | C7: =RES_GSF*HC_PSF_RES | D7: Area times unit rate
A8: Hard costs hotel | B8: $ | C8: =HOTEL_GSF*HC_PSF_HOTEL | D8: Area times unit rate
A9: Hard costs retail | B9: $ | C9: =RETAIL_GSF*HC_PSF_RETAIL | D9: Area times unit rate
A10: Hard costs | B10: $ | C10: =C7+C8+C9 | D10: Sum of hard-cost lines
A11: Contingency | B11: $ | C11: =CONTINGENCY_PCT*C10 | D11: Percent of hard costs
A12: Soft costs | B12: $ | C12: =SOFTCOST_PCT*C10 | D12: Percent of hard costs
A13: FF&E hotel | B13: $ | C13: =HOTEL_KEYS*FFE_PER_KEY | D13: Keys times allowance
A14: FF&E retail | B14: $ | C14: =RETAIL_GSF*FFE_PSF_RETAIL | D14: Area times allowance
A15: FF&E | B15: $ | C15: =C13+C14 | D15: Hotel plus retail
A16: Developer fee base | B16: $ | C16: =C6+C10+C11+C12+C15 | D16: Land, acquisition, hard, contingency, soft, FF&E
A17: Developer fee | B17: $ | C17: =DEVFEE_PCT*C16 | D17: Percent of fee base
A18: Uses excluding interest | B18: $ | C18: =C16+C17 | D18: Fee base plus developer fee
A19: Average SOFR during construction | B19: % | C19: =AVERAGE(SOFR!$C$2:INDEX(SOFR!$C$2:$C$85,CONSTR_MONTHS)) | D19: Arithmetic average of the paste-target forwards
A20: Interest reserve | B20: $ | C20: =LTC_PCT*C18*((C19+CT_SPREAD_PCT)/12)*CONSTR_MONTHS*AVG_DRAWN_FRAC | D20: Linear estimate. No circular interest calculation.
A21: Total uses | B21: $ | C21: =(C18+C20)/(1-LTC_PCT*CT_COSTS_PCT) | D21: Closed form so commitment = LTC% x total uses, with loan costs inside uses.
A22: Construction commitment | B22: $ | C22: =LTC_PCT*C21 | D22: LTC times total uses, including the interest reserve
A23: Construction loan costs | B23: $ | C23: =CT_COSTS_PCT*C22 | D23: Percent of commitment. Permanent financing costs are not here.
A24: Uses component sum | B24: $ | C24: =C18+C20+C23 | D24: Ex-interest plus reserve plus loan costs
A25: Uses tie-out | B25: $ | C25: =C24-C21 | D25: Must be zero
A26: Sources
A27: Source: construction loan | B27: $ | C27: =C22 | D27: Commitment
A28: Source: equity | B28: $ | C28: =C21-C22 | D28: Total uses minus commitment. Contributed at month 1.
A29: Total sources | B29: $ | C29: =C27+C28 | D29: Loan plus equity
A30: GP equity | B30: $ | C30: =C28*GP_EQUITY_PCT | D30: Co-invest share
A31: LP equity | B31: $ | C31: =C28*(1-GP_EQUITY_PCT) | D31: Remainder of equity
A32: Non-land uses on the spend curve | B32: $ | C32: =C10+C11+C12+C15+C17 | D32: Hard, contingency, soft, FF&E, and fee
A33: Sources minus uses | B33: $ | C33: =C29-C21 | D33: Must be zero

Sheet SpendCurve
A1: SpendCurve | D1: Land and loan costs at month 1. Other non-interest uses follow S(t)=(t/CONSTR_MONTHS)^2.2.
A2: Month | B2: index | C2: =COLUMN()-2 | D2: =COLUMN()-2 | E2: =COLUMN()-2 | F2: =COLUMN()-2 | G2: =COLUMN()-2 | H2: =COLUMN()-2 | I2: =COLUMN()-2 | J2: =COLUMN()-2 | ... CH2: =COLUMN()-2
A3: Date | B3: month-end | C3: =EOMONTH(DATE(2026,1,1),C2-1) | D3: =EOMONTH(DATE(2026,1,1),D2-1) | E3: =EOMONTH(DATE(2026,1,1),E2-1) | F3: =EOMONTH(DATE(2026,1,1),F2-1) | G3: =EOMONTH(DATE(2026,1,1),G2-1) | H3: =EOMONTH(DATE(2026,1,1),H2-1) | I3: =EOMONTH(DATE(2026,1,1),I2-1) | J3: =EOMONTH(DATE(2026,1,1),J2-1) | ... CH3: =EOMONTH(DATE(2026,1,1),CH2-1)
A4: Cumulative spend fraction S(t) | B4: fraction | C4: =IF(C2>=CONSTR_MONTHS,1,(C2/CONSTR_MONTHS)^2.2) | D4: =IF(D2>=CONSTR_MONTHS,1,(D2/CONSTR_MONTHS)^2.2) | E4: =IF(E2>=CONSTR_MONTHS,1,(E2/CONSTR_MONTHS)^2.2) | F4: =IF(F2>=CONSTR_MONTHS,1,(F2/CONSTR_MONTHS)^2.2) | G4: =IF(G2>=CONSTR_MONTHS,1,(G2/CONSTR_MONTHS)^2.2) | H4: =IF(H2>=CONSTR_MONTHS,1,(H2/CONSTR_MONTHS)^2.2) | I4: =IF(I2>=CONSTR_MONTHS,1,(I2/CONSTR_MONTHS)^2.2) | J4: =IF(J2>=CONSTR_MONTHS,1,(J2/CONSTR_MONTHS)^2.2) | ... CH4: =IF(CH2>=CONSTR_MONTHS,1,(CH2/CONSTR_MONTHS)^2.2)
A5: Prior cumulative fraction | B5: fraction | C5: =0 | D5: =IF(D2-1>=CONSTR_MONTHS,1,((D2-1)/CONSTR_MONTHS)^2.2) | E5: =IF(E2-1>=CONSTR_MONTHS,1,((E2-1)/CONSTR_MONTHS)^2.2) | F5: =IF(F2-1>=CONSTR_MONTHS,1,((F2-1)/CONSTR_MONTHS)^2.2) | G5: =IF(G2-1>=CONSTR_MONTHS,1,((G2-1)/CONSTR_MONTHS)^2.2) | H5: =IF(H2-1>=CONSTR_MONTHS,1,((H2-1)/CONSTR_MONTHS)^2.2) | I5: =IF(I2-1>=CONSTR_MONTHS,1,((I2-1)/CONSTR_MONTHS)^2.2) | J5: =IF(J2-1>=CONSTR_MONTHS,1,((J2-1)/CONSTR_MONTHS)^2.2) | K5: =IF(K2-1>=CONSTR_MONTHS,1,((K2-1)/CONSTR_MONTHS)^2.2) | ... CH5: =IF(CH2-1>=CONSTR_MONTHS,1,((CH2-1)/CONSTR_MONTHS)^2.2)
A6: Monthly weight | B6: fraction | C6: =C4-C5 | D6: =D4-D5 | E6: =E4-E5 | F6: =F4-F5 | G6: =G4-G5 | H6: =H4-H5 | I6: =I4-I5 | J6: =J4-J5 | ... CH6: =CH4-CH5
A7: Land and acquisition | B7: $ | C7: =IF(C2=1,SourcesUses!$C$6,0) | D7: =IF(D2=1,SourcesUses!$C$6,0) | E7: =IF(E2=1,SourcesUses!$C$6,0) | F7: =IF(F2=1,SourcesUses!$C$6,0) | G7: =IF(G2=1,SourcesUses!$C$6,0) | H7: =IF(H2=1,SourcesUses!$C$6,0) | I7: =IF(I2=1,SourcesUses!$C$6,0) | J7: =IF(J2=1,SourcesUses!$C$6,0) | ... CH7: =IF(CH2=1,SourcesUses!$C$6,0)
A8: Non-land uses | B8: $ | C8: =SourcesUses!$C$32*C6 | D8: =SourcesUses!$C$32*D6 | E8: =SourcesUses!$C$32*E6 | F8: =SourcesUses!$C$32*F6 | G8: =SourcesUses!$C$32*G6 | H8: =SourcesUses!$C$32*H6 | I8: =SourcesUses!$C$32*I6 | J8: =SourcesUses!$C$32*J6 | ... CH8: =SourcesUses!$C$32*CH6
A9: Construction loan costs | B9: $ | C9: =IF(C2=1,SourcesUses!$C$23,0) | D9: =IF(D2=1,SourcesUses!$C$23,0) | E9: =IF(E2=1,SourcesUses!$C$23,0) | F9: =IF(F2=1,SourcesUses!$C$23,0) | G9: =IF(G2=1,SourcesUses!$C$23,0) | H9: =IF(H2=1,SourcesUses!$C$23,0) | I9: =IF(I2=1,SourcesUses!$C$23,0) | J9: =IF(J2=1,SourcesUses!$C$23,0) | ... CH9: =IF(CH2=1,SourcesUses!$C$23,0)
A10: Budget spend | B10: $ | C10: =C7+C8+C9 | D10: =D7+D8+D9 | E10: =E7+E8+E9 | F10: =F7+F8+F9 | G10: =G7+G8+G9 | H10: =H7+H8+H9 | I10: =I7+I8+I9 | J10: =J7+J8+J9 | ... CH10: =CH7+CH8+CH9

Sheet CondoSellout
A1: CondoSellout
A2: Month | B2: index | C2: =COLUMN()-2 | D2: =COLUMN()-2 | E2: =COLUMN()-2 | F2: =COLUMN()-2 | G2: =COLUMN()-2 | H2: =COLUMN()-2 | I2: =COLUMN()-2 | J2: =COLUMN()-2 | ... CH2: =COLUMN()-2
A3: Date | B3: month-end | C3: =EOMONTH(DATE(2026,1,1),C2-1) | D3: =EOMONTH(DATE(2026,1,1),D2-1) | E3: =EOMONTH(DATE(2026,1,1),E2-1) | F3: =EOMONTH(DATE(2026,1,1),F2-1) | G3: =EOMONTH(DATE(2026,1,1),G2-1) | H3: =EOMONTH(DATE(2026,1,1),H2-1) | I3: =EOMONTH(DATE(2026,1,1),I2-1) | J3: =EOMONTH(DATE(2026,1,1),J2-1) | ... CH3: =EOMONTH(DATE(2026,1,1),CH2-1)
A4: Studio closings | B4: units | C4: =IF(AND(C2>=FIRST_CLOSING_M,C2<FIRST_CLOSING_M+CLOSINGS_SPAN_M),ROUNDDOWN(UNITS_STUDIO/CLOSINGS_SPAN_M,0)+IF(C2-FIRST_CLOSING_M+1<=UNITS_STUDIO-ROUNDDOWN(UNITS_STUDIO/CLOSINGS_SPAN_M,0)*CLOSINGS_SPAN_M,1,0),0) | D4: =IF(AND(D2>=FIRST_CLOSING_M,D2<FIRST_CLOSING_M+CLOSINGS_SPAN_M),ROUNDDOWN(UNITS_STUDIO/CLOSINGS_SPAN_M,0)+IF(D2-FIRST_CLOSING_M+1<=UNITS_STUDIO-ROUNDDOWN(UNITS_STUDIO/CLOSINGS_SPAN_M,0)*CLOSINGS_SPAN_M,1,0),0) | E4: =IF(AND(E2>=FIRST_CLOSING_M,E2<FIRST_CLOSING_M+CLOSINGS_SPAN_M),ROUNDDOWN(UNITS_STUDIO/CLOSINGS_SPAN_M,0)+IF(E2-FIRST_CLOSING_M+1<=UNITS_STUDIO-ROUNDDOWN(UNITS_STUDIO/CLOSINGS_SPAN_M,0)*CLOSINGS_SPAN_M,1,0),0) | F4: =IF(AND(F2>=FIRST_CLOSING_M,F2<FIRST_CLOSING_M+CLOSINGS_SPAN_M),ROUNDDOWN(UNITS_STUDIO/CLOSINGS_SPAN_M,0)+IF(F2-FIRST_CLOSING_M+1<=UNITS_STUDIO-ROUNDDOWN(UNITS_STUDIO/CLOSINGS_SPAN_M,0)*CLOSINGS_SPAN_M,1,0),0) | G4: =IF(AND(G2>=FIRST_CLOSING_M,G2<FIRST_CLOSING_M+CLOSINGS_SPAN_M),ROUNDDOWN(UNITS_STUDIO/CLOSINGS_SPAN_M,0)+IF(G2-FIRST_CLOSING_M+1<=UNITS_STUDIO-ROUNDDOWN(UNITS_STUDIO/CLOSINGS_SPAN_M,0)*CLOSINGS_SPAN_M,1,0),0) | H4: =IF(AND(H2>=FIRST_CLOSING_M,H2<FIRST_CLOSING_M+CLOSINGS_SPAN_M),ROUNDDOWN(UNITS_STUDIO/CLOSINGS_SPAN_M,0)+IF(H2-FIRST_CLOSING_M+1<=UNITS_STUDIO-ROUNDDOWN(UNITS_STUDIO/CLOSINGS_SPAN_M,0)*CLOSINGS_SPAN_M,1,0),0) | I4: =IF(AND(I2>=FIRST_CLOSING_M,I2<FIRST_CLOSING_M+CLOSINGS_SPAN_M),ROUNDDOWN(UNITS_STUDIO/CLOSINGS_SPAN_M,0)+IF(I2-FIRST_CLOSING_M+1<=UNITS_STUDIO-ROUNDDOWN(UNITS_STUDIO/CLOSINGS_SPAN_M,0)*CLOSINGS_SPAN_M,1,0),0) | J4: =IF(AND(J2>=FIRST_CLOSING_M,J2<FIRST_CLOSING_M+CLOSINGS_SPAN_M),ROUNDDOWN(UNITS_STUDIO/CLOSINGS_SPAN_M,0)+IF(J2-FIRST_CLOSING_M+1<=UNITS_STUDIO-ROUNDDOWN(UNITS_STUDIO/CLOSINGS_SPAN_M,0)*CLOSINGS_SPAN_M,1,0),0) | ... CH4: =IF(AND(CH2>=FIRST_CLOSING_M,CH2<FIRST_CLOSING_M+CLOSINGS_SPAN_M),ROUNDDOWN(UNITS_STUDIO/CLOSINGS_SPAN_M,0)+IF(CH2-FIRST_CLOSING_M+1<=UNITS_STUDIO-ROUNDDOWN(UNITS_STUDIO/CLOSINGS_SPAN_M,0)*CLOSINGS_SPAN_M,1,0),0)
A5: One-bedroom closings | B5: units | C5: =IF(AND(C2>=FIRST_CLOSING_M,C2<FIRST_CLOSING_M+CLOSINGS_SPAN_M),ROUNDDOWN(UNITS_1BR/CLOSINGS_SPAN_M,0)+IF(C2-FIRST_CLOSING_M+1<=UNITS_1BR-ROUNDDOWN(UNITS_1BR/CLOSINGS_SPAN_M,0)*CLOSINGS_SPAN_M,1,0),0) | D5: =IF(AND(D2>=FIRST_CLOSING_M,D2<FIRST_CLOSING_M+CLOSINGS_SPAN_M),ROUNDDOWN(UNITS_1BR/CLOSINGS_SPAN_M,0)+IF(D2-FIRST_CLOSING_M+1<=UNITS_1BR-ROUNDDOWN(UNITS_1BR/CLOSINGS_SPAN_M,0)*CLOSINGS_SPAN_M,1,0),0) | E5: =IF(AND(E2>=FIRST_CLOSING_M,E2<FIRST_CLOSING_M+CLOSINGS_SPAN_M),ROUNDDOWN(UNITS_1BR/CLOSINGS_SPAN_M,0)+IF(E2-FIRST_CLOSING_M+1<=UNITS_1BR-ROUNDDOWN(UNITS_1BR/CLOSINGS_SPAN_M,0)*CLOSINGS_SPAN_M,1,0),0) | F5: =IF(AND(F2>=FIRST_CLOSING_M,F2<FIRST_CLOSING_M+CLOSINGS_SPAN_M),ROUNDDOWN(UNITS_1BR/CLOSINGS_SPAN_M,0)+IF(F2-FIRST_CLOSING_M+1<=UNITS_1BR-ROUNDDOWN(UNITS_1BR/CLOSINGS_SPAN_M,0)*CLOSINGS_SPAN_M,1,0),0) | G5: =IF(AND(G2>=FIRST_CLOSING_M,G2<FIRST_CLOSING_M+CLOSINGS_SPAN_M),ROUNDDOWN(UNITS_1BR/CLOSINGS_SPAN_M,0)+IF(G2-FIRST_CLOSING_M+1<=UNITS_1BR-ROUNDDOWN(UNITS_1BR/CLOSINGS_SPAN_M,0)*CLOSINGS_SPAN_M,1,0),0) | H5: =IF(AND(H2>=FIRST_CLOSING_M,H2<FIRST_CLOSING_M+CLOSINGS_SPAN_M),ROUNDDOWN(UNITS_1BR/CLOSINGS_SPAN_M,0)+IF(H2-FIRST_CLOSING_M+1<=UNITS_1BR-ROUNDDOWN(UNITS_1BR/CLOSINGS_SPAN_M,0)*CLOSINGS_SPAN_M,1,0),0) | I5: =IF(AND(I2>=FIRST_CLOSING_M,I2<FIRST_CLOSING_M+CLOSINGS_SPAN_M),ROUNDDOWN(UNITS_1BR/CLOSINGS_SPAN_M,0)+IF(I2-FIRST_CLOSING_M+1<=UNITS_1BR-ROUNDDOWN(UNITS_1BR/CLOSINGS_SPAN_M,0)*CLOSINGS_SPAN_M,1,0),0) | J5: =IF(AND(J2>=FIRST_CLOSING_M,J2<FIRST_CLOSING_M+CLOSINGS_SPAN_M),ROUNDDOWN(UNITS_1BR/CLOSINGS_SPAN_M,0)+IF(J2-FIRST_CLOSING_M+1<=UNITS_1BR-ROUNDDOWN(UNITS_1BR/CLOSINGS_SPAN_M,0)*CLOSINGS_SPAN_M,1,0),0) | ... CH5: =IF(AND(CH2>=FIRST_CLOSING_M,CH2<FIRST_CLOSING_M+CLOSINGS_SPAN_M),ROUNDDOWN(UNITS_1BR/CLOSINGS_SPAN_M,0)+IF(CH2-FIRST_CLOSING_M+1<=UNITS_1BR-ROUNDDOWN(UNITS_1BR/CLOSINGS_SPAN_M,0)*CLOSINGS_SPAN_M,1,0),0)
A6: Two-bedroom closings | B6: units | C6: =IF(AND(C2>=FIRST_CLOSING_M,C2<FIRST_CLOSING_M+CLOSINGS_SPAN_M),ROUNDDOWN(UNITS_2BR/CLOSINGS_SPAN_M,0)+IF(C2-FIRST_CLOSING_M+1<=UNITS_2BR-ROUNDDOWN(UNITS_2BR/CLOSINGS_SPAN_M,0)*CLOSINGS_SPAN_M,1,0),0) | D6: =IF(AND(D2>=FIRST_CLOSING_M,D2<FIRST_CLOSING_M+CLOSINGS_SPAN_M),ROUNDDOWN(UNITS_2BR/CLOSINGS_SPAN_M,0)+IF(D2-FIRST_CLOSING_M+1<=UNITS_2BR-ROUNDDOWN(UNITS_2BR/CLOSINGS_SPAN_M,0)*CLOSINGS_SPAN_M,1,0),0) | E6: =IF(AND(E2>=FIRST_CLOSING_M,E2<FIRST_CLOSING_M+CLOSINGS_SPAN_M),ROUNDDOWN(UNITS_2BR/CLOSINGS_SPAN_M,0)+IF(E2-FIRST_CLOSING_M+1<=UNITS_2BR-ROUNDDOWN(UNITS_2BR/CLOSINGS_SPAN_M,0)*CLOSINGS_SPAN_M,1,0),0) | F6: =IF(AND(F2>=FIRST_CLOSING_M,F2<FIRST_CLOSING_M+CLOSINGS_SPAN_M),ROUNDDOWN(UNITS_2BR/CLOSINGS_SPAN_M,0)+IF(F2-FIRST_CLOSING_M+1<=UNITS_2BR-ROUNDDOWN(UNITS_2BR/CLOSINGS_SPAN_M,0)*CLOSINGS_SPAN_M,1,0),0) | G6: =IF(AND(G2>=FIRST_CLOSING_M,G2<FIRST_CLOSING_M+CLOSINGS_SPAN_M),ROUNDDOWN(UNITS_2BR/CLOSINGS_SPAN_M,0)+IF(G2-FIRST_CLOSING_M+1<=UNITS_2BR-ROUNDDOWN(UNITS_2BR/CLOSINGS_SPAN_M,0)*CLOSINGS_SPAN_M,1,0),0) | H6: =IF(AND(H2>=FIRST_CLOSING_M,H2<FIRST_CLOSING_M+CLOSINGS_SPAN_M),ROUNDDOWN(UNITS_2BR/CLOSINGS_SPAN_M,0)+IF(H2-FIRST_CLOSING_M+1<=UNITS_2BR-ROUNDDOWN(UNITS_2BR/CLOSINGS_SPAN_M,0)*CLOSINGS_SPAN_M,1,0),0) | I6: =IF(AND(I2>=FIRST_CLOSING_M,I2<FIRST_CLOSING_M+CLOSINGS_SPAN_M),ROUNDDOWN(UNITS_2BR/CLOSINGS_SPAN_M,0)+IF(I2-FIRST_CLOSING_M+1<=UNITS_2BR-ROUNDDOWN(UNITS_2BR/CLOSINGS_SPAN_M,0)*CLOSINGS_SPAN_M,1,0),0) | J6: =IF(AND(J2>=FIRST_CLOSING_M,J2<FIRST_CLOSING_M+CLOSINGS_SPAN_M),ROUNDDOWN(UNITS_2BR/CLOSINGS_SPAN_M,0)+IF(J2-FIRST_CLOSING_M+1<=UNITS_2BR-ROUNDDOWN(UNITS_2BR/CLOSINGS_SPAN_M,0)*CLOSINGS_SPAN_M,1,0),0) | ... CH6: =IF(AND(CH2>=FIRST_CLOSING_M,CH2<FIRST_CLOSING_M+CLOSINGS_SPAN_M),ROUNDDOWN(UNITS_2BR/CLOSINGS_SPAN_M,0)+IF(CH2-FIRST_CLOSING_M+1<=UNITS_2BR-ROUNDDOWN(UNITS_2BR/CLOSINGS_SPAN_M,0)*CLOSINGS_SPAN_M,1,0),0)
A7: Three-bedroom closings | B7: units | C7: =IF(AND(C2>=FIRST_CLOSING_M,C2<FIRST_CLOSING_M+CLOSINGS_SPAN_M),ROUNDDOWN(UNITS_3BR/CLOSINGS_SPAN_M,0)+IF(C2-FIRST_CLOSING_M+1<=UNITS_3BR-ROUNDDOWN(UNITS_3BR/CLOSINGS_SPAN_M,0)*CLOSINGS_SPAN_M,1,0),0) | D7: =IF(AND(D2>=FIRST_CLOSING_M,D2<FIRST_CLOSING_M+CLOSINGS_SPAN_M),ROUNDDOWN(UNITS_3BR/CLOSINGS_SPAN_M,0)+IF(D2-FIRST_CLOSING_M+1<=UNITS_3BR-ROUNDDOWN(UNITS_3BR/CLOSINGS_SPAN_M,0)*CLOSINGS_SPAN_M,1,0),0) | E7: =IF(AND(E2>=FIRST_CLOSING_M,E2<FIRST_CLOSING_M+CLOSINGS_SPAN_M),ROUNDDOWN(UNITS_3BR/CLOSINGS_SPAN_M,0)+IF(E2-FIRST_CLOSING_M+1<=UNITS_3BR-ROUNDDOWN(UNITS_3BR/CLOSINGS_SPAN_M,0)*CLOSINGS_SPAN_M,1,0),0) | F7: =IF(AND(F2>=FIRST_CLOSING_M,F2<FIRST_CLOSING_M+CLOSINGS_SPAN_M),ROUNDDOWN(UNITS_3BR/CLOSINGS_SPAN_M,0)+IF(F2-FIRST_CLOSING_M+1<=UNITS_3BR-ROUNDDOWN(UNITS_3BR/CLOSINGS_SPAN_M,0)*CLOSINGS_SPAN_M,1,0),0) | G7: =IF(AND(G2>=FIRST_CLOSING_M,G2<FIRST_CLOSING_M+CLOSINGS_SPAN_M),ROUNDDOWN(UNITS_3BR/CLOSINGS_SPAN_M,0)+IF(G2-FIRST_CLOSING_M+1<=UNITS_3BR-ROUNDDOWN(UNITS_3BR/CLOSINGS_SPAN_M,0)*CLOSINGS_SPAN_M,1,0),0) | H7: =IF(AND(H2>=FIRST_CLOSING_M,H2<FIRST_CLOSING_M+CLOSINGS_SPAN_M),ROUNDDOWN(UNITS_3BR/CLOSINGS_SPAN_M,0)+IF(H2-FIRST_CLOSING_M+1<=UNITS_3BR-ROUNDDOWN(UNITS_3BR/CLOSINGS_SPAN_M,0)*CLOSINGS_SPAN_M,1,0),0) | I7: =IF(AND(I2>=FIRST_CLOSING_M,I2<FIRST_CLOSING_M+CLOSINGS_SPAN_M),ROUNDDOWN(UNITS_3BR/CLOSINGS_SPAN_M,0)+IF(I2-FIRST_CLOSING_M+1<=UNITS_3BR-ROUNDDOWN(UNITS_3BR/CLOSINGS_SPAN_M,0)*CLOSINGS_SPAN_M,1,0),0) | J7: =IF(AND(J2>=FIRST_CLOSING_M,J2<FIRST_CLOSING_M+CLOSINGS_SPAN_M),ROUNDDOWN(UNITS_3BR/CLOSINGS_SPAN_M,0)+IF(J2-FIRST_CLOSING_M+1<=UNITS_3BR-ROUNDDOWN(UNITS_3BR/CLOSINGS_SPAN_M,0)*CLOSINGS_SPAN_M,1,0),0) | ... CH7: =IF(AND(CH2>=FIRST_CLOSING_M,CH2<FIRST_CLOSING_M+CLOSINGS_SPAN_M),ROUNDDOWN(UNITS_3BR/CLOSINGS_SPAN_M,0)+IF(CH2-FIRST_CLOSING_M+1<=UNITS_3BR-ROUNDDOWN(UNITS_3BR/CLOSINGS_SPAN_M,0)*CLOSINGS_SPAN_M,1,0),0)
A8: Penthouse closings | B8: units | C8: =IF(AND(C2>=FIRST_CLOSING_M,C2<FIRST_CLOSING_M+CLOSINGS_SPAN_M),ROUNDDOWN(UNITS_PH/CLOSINGS_SPAN_M,0)+IF(C2-FIRST_CLOSING_M+1<=UNITS_PH-ROUNDDOWN(UNITS_PH/CLOSINGS_SPAN_M,0)*CLOSINGS_SPAN_M,1,0),0) | D8: =IF(AND(D2>=FIRST_CLOSING_M,D2<FIRST_CLOSING_M+CLOSINGS_SPAN_M),ROUNDDOWN(UNITS_PH/CLOSINGS_SPAN_M,0)+IF(D2-FIRST_CLOSING_M+1<=UNITS_PH-ROUNDDOWN(UNITS_PH/CLOSINGS_SPAN_M,0)*CLOSINGS_SPAN_M,1,0),0) | E8: =IF(AND(E2>=FIRST_CLOSING_M,E2<FIRST_CLOSING_M+CLOSINGS_SPAN_M),ROUNDDOWN(UNITS_PH/CLOSINGS_SPAN_M,0)+IF(E2-FIRST_CLOSING_M+1<=UNITS_PH-ROUNDDOWN(UNITS_PH/CLOSINGS_SPAN_M,0)*CLOSINGS_SPAN_M,1,0),0) | F8: =IF(AND(F2>=FIRST_CLOSING_M,F2<FIRST_CLOSING_M+CLOSINGS_SPAN_M),ROUNDDOWN(UNITS_PH/CLOSINGS_SPAN_M,0)+IF(F2-FIRST_CLOSING_M+1<=UNITS_PH-ROUNDDOWN(UNITS_PH/CLOSINGS_SPAN_M,0)*CLOSINGS_SPAN_M,1,0),0) | G8: =IF(AND(G2>=FIRST_CLOSING_M,G2<FIRST_CLOSING_M+CLOSINGS_SPAN_M),ROUNDDOWN(UNITS_PH/CLOSINGS_SPAN_M,0)+IF(G2-FIRST_CLOSING_M+1<=UNITS_PH-ROUNDDOWN(UNITS_PH/CLOSINGS_SPAN_M,0)*CLOSINGS_SPAN_M,1,0),0) | H8: =IF(AND(H2>=FIRST_CLOSING_M,H2<FIRST_CLOSING_M+CLOSINGS_SPAN_M),ROUNDDOWN(UNITS_PH/CLOSINGS_SPAN_M,0)+IF(H2-FIRST_CLOSING_M+1<=UNITS_PH-ROUNDDOWN(UNITS_PH/CLOSINGS_SPAN_M,0)*CLOSINGS_SPAN_M,1,0),0) | I8: =IF(AND(I2>=FIRST_CLOSING_M,I2<FIRST_CLOSING_M+CLOSINGS_SPAN_M),ROUNDDOWN(UNITS_PH/CLOSINGS_SPAN_M,0)+IF(I2-FIRST_CLOSING_M+1<=UNITS_PH-ROUNDDOWN(UNITS_PH/CLOSINGS_SPAN_M,0)*CLOSINGS_SPAN_M,1,0),0) | J8: =IF(AND(J2>=FIRST_CLOSING_M,J2<FIRST_CLOSING_M+CLOSINGS_SPAN_M),ROUNDDOWN(UNITS_PH/CLOSINGS_SPAN_M,0)+IF(J2-FIRST_CLOSING_M+1<=UNITS_PH-ROUNDDOWN(UNITS_PH/CLOSINGS_SPAN_M,0)*CLOSINGS_SPAN_M,1,0),0) | ... CH8: =IF(AND(CH2>=FIRST_CLOSING_M,CH2<FIRST_CLOSING_M+CLOSINGS_SPAN_M),ROUNDDOWN(UNITS_PH/CLOSINGS_SPAN_M,0)+IF(CH2-FIRST_CLOSING_M+1<=UNITS_PH-ROUNDDOWN(UNITS_PH/CLOSINGS_SPAN_M,0)*CLOSINGS_SPAN_M,1,0),0)
A9: Total unit closings | B9: units | C9: =C4+C5+C6+C7+C8 | D9: =D4+D5+D6+D7+D8 | E9: =E4+E5+E6+E7+E8 | F9: =F4+F5+F6+F7+F8 | G9: =G4+G5+G6+G7+G8 | H9: =H4+H5+H6+H7+H8 | I9: =I4+I5+I6+I7+I8 | J9: =J4+J5+J6+J7+J8 | ... CH9: =CH4+CH5+CH6+CH7+CH8
A10: Unit revenue | B10: $ | C10: =C4*SQFT_STUDIO*PPSF_STUDIO+C5*SQFT_1BR*PPSF_1BR+C6*SQFT_2BR*PPSF_2BR+C7*SQFT_3BR*PPSF_3BR+C8*SQFT_PH*PPSF_PH | D10: =D4*SQFT_STUDIO*PPSF_STUDIO+D5*SQFT_1BR*PPSF_1BR+D6*SQFT_2BR*PPSF_2BR+D7*SQFT_3BR*PPSF_3BR+D8*SQFT_PH*PPSF_PH | E10: =E4*SQFT_STUDIO*PPSF_STUDIO+E5*SQFT_1BR*PPSF_1BR+E6*SQFT_2BR*PPSF_2BR+E7*SQFT_3BR*PPSF_3BR+E8*SQFT_PH*PPSF_PH | F10: =F4*SQFT_STUDIO*PPSF_STUDIO+F5*SQFT_1BR*PPSF_1BR+F6*SQFT_2BR*PPSF_2BR+F7*SQFT_3BR*PPSF_3BR+F8*SQFT_PH*PPSF_PH | G10: =G4*SQFT_STUDIO*PPSF_STUDIO+G5*SQFT_1BR*PPSF_1BR+G6*SQFT_2BR*PPSF_2BR+G7*SQFT_3BR*PPSF_3BR+G8*SQFT_PH*PPSF_PH | H10: =H4*SQFT_STUDIO*PPSF_STUDIO+H5*SQFT_1BR*PPSF_1BR+H6*SQFT_2BR*PPSF_2BR+H7*SQFT_3BR*PPSF_3BR+H8*SQFT_PH*PPSF_PH | I10: =I4*SQFT_STUDIO*PPSF_STUDIO+I5*SQFT_1BR*PPSF_1BR+I6*SQFT_2BR*PPSF_2BR+I7*SQFT_3BR*PPSF_3BR+I8*SQFT_PH*PPSF_PH | J10: =J4*SQFT_STUDIO*PPSF_STUDIO+J5*SQFT_1BR*PPSF_1BR+J6*SQFT_2BR*PPSF_2BR+J7*SQFT_3BR*PPSF_3BR+J8*SQFT_PH*PPSF_PH | ... CH10: =CH4*SQFT_STUDIO*PPSF_STUDIO+CH5*SQFT_1BR*PPSF_1BR+CH6*SQFT_2BR*PPSF_2BR+CH7*SQFT_3BR*PPSF_3BR+CH8*SQFT_PH*PPSF_PH
A11: Parking spaces released | B11: spaces | C11: =PARKING_SPACES*C9/(UNITS_STUDIO+UNITS_1BR+UNITS_2BR+UNITS_3BR+UNITS_PH) | D11: =PARKING_SPACES*D9/(UNITS_STUDIO+UNITS_1BR+UNITS_2BR+UNITS_3BR+UNITS_PH) | E11: =PARKING_SPACES*E9/(UNITS_STUDIO+UNITS_1BR+UNITS_2BR+UNITS_3BR+UNITS_PH) | F11: =PARKING_SPACES*F9/(UNITS_STUDIO+UNITS_1BR+UNITS_2BR+UNITS_3BR+UNITS_PH) | G11: =PARKING_SPACES*G9/(UNITS_STUDIO+UNITS_1BR+UNITS_2BR+UNITS_3BR+UNITS_PH) | H11: =PARKING_SPACES*H9/(UNITS_STUDIO+UNITS_1BR+UNITS_2BR+UNITS_3BR+UNITS_PH) | I11: =PARKING_SPACES*I9/(UNITS_STUDIO+UNITS_1BR+UNITS_2BR+UNITS_3BR+UNITS_PH) | J11: =PARKING_SPACES*J9/(UNITS_STUDIO+UNITS_1BR+UNITS_2BR+UNITS_3BR+UNITS_PH) | ... CH11: =PARKING_SPACES*CH9/(UNITS_STUDIO+UNITS_1BR+UNITS_2BR+UNITS_3BR+UNITS_PH)
A12: Storage units released | B12: units | C12: =STORAGE_UNITS*C9/(UNITS_STUDIO+UNITS_1BR+UNITS_2BR+UNITS_3BR+UNITS_PH) | D12: =STORAGE_UNITS*D9/(UNITS_STUDIO+UNITS_1BR+UNITS_2BR+UNITS_3BR+UNITS_PH) | E12: =STORAGE_UNITS*E9/(UNITS_STUDIO+UNITS_1BR+UNITS_2BR+UNITS_3BR+UNITS_PH) | F12: =STORAGE_UNITS*F9/(UNITS_STUDIO+UNITS_1BR+UNITS_2BR+UNITS_3BR+UNITS_PH) | G12: =STORAGE_UNITS*G9/(UNITS_STUDIO+UNITS_1BR+UNITS_2BR+UNITS_3BR+UNITS_PH) | H12: =STORAGE_UNITS*H9/(UNITS_STUDIO+UNITS_1BR+UNITS_2BR+UNITS_3BR+UNITS_PH) | I12: =STORAGE_UNITS*I9/(UNITS_STUDIO+UNITS_1BR+UNITS_2BR+UNITS_3BR+UNITS_PH) | J12: =STORAGE_UNITS*J9/(UNITS_STUDIO+UNITS_1BR+UNITS_2BR+UNITS_3BR+UNITS_PH) | ... CH12: =STORAGE_UNITS*CH9/(UNITS_STUDIO+UNITS_1BR+UNITS_2BR+UNITS_3BR+UNITS_PH)
A13: Parking revenue | B13: $ | C13: =C11*PARKING_PRICE | D13: =D11*PARKING_PRICE | E13: =E11*PARKING_PRICE | F13: =F11*PARKING_PRICE | G13: =G11*PARKING_PRICE | H13: =H11*PARKING_PRICE | I13: =I11*PARKING_PRICE | J13: =J11*PARKING_PRICE | ... CH13: =CH11*PARKING_PRICE
A14: Storage revenue | B14: $ | C14: =C12*STORAGE_PRICE | D14: =D12*STORAGE_PRICE | E14: =E12*STORAGE_PRICE | F14: =F12*STORAGE_PRICE | G14: =G12*STORAGE_PRICE | H14: =H12*STORAGE_PRICE | I14: =I12*STORAGE_PRICE | J14: =J12*STORAGE_PRICE | ... CH14: =CH12*STORAGE_PRICE
A15: Gross revenue | B15: $ | C15: =C10+C13+C14 | D15: =D10+D13+D14 | E15: =E10+E13+E14 | F15: =F10+F13+F14 | G15: =G10+G13+G14 | H15: =H10+H13+H14 | I15: =I10+I13+I14 | J15: =J10+J13+J14 | ... CH15: =CH10+CH13+CH14
A16: Net revenue | B16: $ | C16: =C15*(1-CLOSING_COST_PCT-MARKETING_PCT) | D16: =D15*(1-CLOSING_COST_PCT-MARKETING_PCT) | E16: =E15*(1-CLOSING_COST_PCT-MARKETING_PCT) | F16: =F15*(1-CLOSING_COST_PCT-MARKETING_PCT) | G16: =G15*(1-CLOSING_COST_PCT-MARKETING_PCT) | H16: =H15*(1-CLOSING_COST_PCT-MARKETING_PCT) | I16: =I15*(1-CLOSING_COST_PCT-MARKETING_PCT) | J16: =J15*(1-CLOSING_COST_PCT-MARKETING_PCT) | ... CH16: =CH15*(1-CLOSING_COST_PCT-MARKETING_PCT)

Sheet RetailProForma
A1: RetailProForma
A2: Month | B2: index | C2: =COLUMN()-2 | D2: =COLUMN()-2 | E2: =COLUMN()-2 | F2: =COLUMN()-2 | G2: =COLUMN()-2 | H2: =COLUMN()-2 | I2: =COLUMN()-2 | J2: =COLUMN()-2 | ... CH2: =COLUMN()-2
A3: Date | B3: month-end | C3: =EOMONTH(DATE(2026,1,1),C2-1) | D3: =EOMONTH(DATE(2026,1,1),D2-1) | E3: =EOMONTH(DATE(2026,1,1),E2-1) | F3: =EOMONTH(DATE(2026,1,1),F2-1) | G3: =EOMONTH(DATE(2026,1,1),G2-1) | H3: =EOMONTH(DATE(2026,1,1),H2-1) | I3: =EOMONTH(DATE(2026,1,1),I2-1) | J3: =EOMONTH(DATE(2026,1,1),J2-1) | ... CH3: =EOMONTH(DATE(2026,1,1),CH2-1)
A4: Operating | B4: 1/0 | C4: =IF(C2>=RETAIL_OPEN_M,1,0) | D4: =IF(D2>=RETAIL_OPEN_M,1,0) | E4: =IF(E2>=RETAIL_OPEN_M,1,0) | F4: =IF(F2>=RETAIL_OPEN_M,1,0) | G4: =IF(G2>=RETAIL_OPEN_M,1,0) | H4: =IF(H2>=RETAIL_OPEN_M,1,0) | I4: =IF(I2>=RETAIL_OPEN_M,1,0) | J4: =IF(J2>=RETAIL_OPEN_M,1,0) | ... CH4: =IF(CH2>=RETAIL_OPEN_M,1,0)
A5: Months from open | B5: months | C5: =IF(C4=1,C2-RETAIL_OPEN_M,0) | D5: =IF(D4=1,D2-RETAIL_OPEN_M,0) | E5: =IF(E4=1,E2-RETAIL_OPEN_M,0) | F5: =IF(F4=1,F2-RETAIL_OPEN_M,0) | G5: =IF(G4=1,G2-RETAIL_OPEN_M,0) | H5: =IF(H4=1,H2-RETAIL_OPEN_M,0) | I5: =IF(I4=1,I2-RETAIL_OPEN_M,0) | J5: =IF(J4=1,J2-RETAIL_OPEN_M,0) | ... CH5: =IF(CH4=1,CH2-RETAIL_OPEN_M,0)
A6: Escalation year index | B6: year | C6: =IF(C4=1,INT(C5/12),0) | D6: =IF(D4=1,INT(D5/12),0) | E6: =IF(E4=1,INT(E5/12),0) | F6: =IF(F4=1,INT(F5/12),0) | G6: =IF(G4=1,INT(G5/12),0) | H6: =IF(H4=1,INT(H5/12),0) | I6: =IF(I4=1,INT(I5/12),0) | J6: =IF(J4=1,INT(J5/12),0) | ... CH6: =IF(CH4=1,INT(CH5/12),0)
A7: Base rent | B7: $ | C7: =IF(C4=1,RETAIL_BASE_PSF*(1+RETAIL_ESC_PCT)^C6*RETAIL_GSF/12,0) | D7: =IF(D4=1,RETAIL_BASE_PSF*(1+RETAIL_ESC_PCT)^D6*RETAIL_GSF/12,0) | E7: =IF(E4=1,RETAIL_BASE_PSF*(1+RETAIL_ESC_PCT)^E6*RETAIL_GSF/12,0) | F7: =IF(F4=1,RETAIL_BASE_PSF*(1+RETAIL_ESC_PCT)^F6*RETAIL_GSF/12,0) | G7: =IF(G4=1,RETAIL_BASE_PSF*(1+RETAIL_ESC_PCT)^G6*RETAIL_GSF/12,0) | H7: =IF(H4=1,RETAIL_BASE_PSF*(1+RETAIL_ESC_PCT)^H6*RETAIL_GSF/12,0) | I7: =IF(I4=1,RETAIL_BASE_PSF*(1+RETAIL_ESC_PCT)^I6*RETAIL_GSF/12,0) | J7: =IF(J4=1,RETAIL_BASE_PSF*(1+RETAIL_ESC_PCT)^J6*RETAIL_GSF/12,0) | ... CH7: =IF(CH4=1,RETAIL_BASE_PSF*(1+RETAIL_ESC_PCT)^CH6*RETAIL_GSF/12,0)
A8: Recovery income | B8: $ | C8: =IF(C4=1,RETAIL_RECOV_PSF*(1+RETAIL_ESC_PCT)^C6*RETAIL_GSF*RETAIL_RECOV_RATIO/12,0) | D8: =IF(D4=1,RETAIL_RECOV_PSF*(1+RETAIL_ESC_PCT)^D6*RETAIL_GSF*RETAIL_RECOV_RATIO/12,0) | E8: =IF(E4=1,RETAIL_RECOV_PSF*(1+RETAIL_ESC_PCT)^E6*RETAIL_GSF*RETAIL_RECOV_RATIO/12,0) | F8: =IF(F4=1,RETAIL_RECOV_PSF*(1+RETAIL_ESC_PCT)^F6*RETAIL_GSF*RETAIL_RECOV_RATIO/12,0) | G8: =IF(G4=1,RETAIL_RECOV_PSF*(1+RETAIL_ESC_PCT)^G6*RETAIL_GSF*RETAIL_RECOV_RATIO/12,0) | H8: =IF(H4=1,RETAIL_RECOV_PSF*(1+RETAIL_ESC_PCT)^H6*RETAIL_GSF*RETAIL_RECOV_RATIO/12,0) | I8: =IF(I4=1,RETAIL_RECOV_PSF*(1+RETAIL_ESC_PCT)^I6*RETAIL_GSF*RETAIL_RECOV_RATIO/12,0) | J8: =IF(J4=1,RETAIL_RECOV_PSF*(1+RETAIL_ESC_PCT)^J6*RETAIL_GSF*RETAIL_RECOV_RATIO/12,0) | ... CH8: =IF(CH4=1,RETAIL_RECOV_PSF*(1+RETAIL_ESC_PCT)^CH6*RETAIL_GSF*RETAIL_RECOV_RATIO/12,0)
A9: EGI | B9: $ | C9: =IF(C4=1,(C7+C8)*(1-RETAIL_VAC_PCT),0) | D9: =IF(D4=1,(D7+D8)*(1-RETAIL_VAC_PCT),0) | E9: =IF(E4=1,(E7+E8)*(1-RETAIL_VAC_PCT),0) | F9: =IF(F4=1,(F7+F8)*(1-RETAIL_VAC_PCT),0) | G9: =IF(G4=1,(G7+G8)*(1-RETAIL_VAC_PCT),0) | H9: =IF(H4=1,(H7+H8)*(1-RETAIL_VAC_PCT),0) | I9: =IF(I4=1,(I7+I8)*(1-RETAIL_VAC_PCT),0) | J9: =IF(J4=1,(J7+J8)*(1-RETAIL_VAC_PCT),0) | ... CH9: =IF(CH4=1,(CH7+CH8)*(1-RETAIL_VAC_PCT),0)
A10: Non-recoverable opex | B10: $ | C10: =IF(C4=1,RETAIL_OP_PSF*RETAIL_GSF/12,0) | D10: =IF(D4=1,RETAIL_OP_PSF*RETAIL_GSF/12,0) | E10: =IF(E4=1,RETAIL_OP_PSF*RETAIL_GSF/12,0) | F10: =IF(F4=1,RETAIL_OP_PSF*RETAIL_GSF/12,0) | G10: =IF(G4=1,RETAIL_OP_PSF*RETAIL_GSF/12,0) | H10: =IF(H4=1,RETAIL_OP_PSF*RETAIL_GSF/12,0) | I10: =IF(I4=1,RETAIL_OP_PSF*RETAIL_GSF/12,0) | J10: =IF(J4=1,RETAIL_OP_PSF*RETAIL_GSF/12,0) | ... CH10: =IF(CH4=1,RETAIL_OP_PSF*RETAIL_GSF/12,0)
A11: Management fee | B11: $ | C11: =RETAIL_MGMT_PCT*C9 | D11: =RETAIL_MGMT_PCT*D9 | E11: =RETAIL_MGMT_PCT*E9 | F11: =RETAIL_MGMT_PCT*F9 | G11: =RETAIL_MGMT_PCT*G9 | H11: =RETAIL_MGMT_PCT*H9 | I11: =RETAIL_MGMT_PCT*I9 | J11: =RETAIL_MGMT_PCT*J9 | ... CH11: =RETAIL_MGMT_PCT*CH9
A12: Retail NOI | B12: $ | C12: =C9-C10-C11 | D12: =D9-D10-D11 | E12: =E9-E10-E11 | F12: =F9-F10-F11 | G12: =G9-G10-G11 | H12: =H9-H10-H11 | I12: =I9-I10-I11 | J12: =J9-J10-J11 | ... CH12: =CH9-CH10-CH11

Sheet HotelProForma
A1: HotelProForma
A2: Month | B2: index | C2: =COLUMN()-2 | D2: =COLUMN()-2 | E2: =COLUMN()-2 | F2: =COLUMN()-2 | G2: =COLUMN()-2 | H2: =COLUMN()-2 | I2: =COLUMN()-2 | J2: =COLUMN()-2 | ... CH2: =COLUMN()-2
A3: Date | B3: month-end | C3: =EOMONTH(DATE(2026,1,1),C2-1) | D3: =EOMONTH(DATE(2026,1,1),D2-1) | E3: =EOMONTH(DATE(2026,1,1),E2-1) | F3: =EOMONTH(DATE(2026,1,1),F2-1) | G3: =EOMONTH(DATE(2026,1,1),G2-1) | H3: =EOMONTH(DATE(2026,1,1),H2-1) | I3: =EOMONTH(DATE(2026,1,1),I2-1) | J3: =EOMONTH(DATE(2026,1,1),J2-1) | ... CH3: =EOMONTH(DATE(2026,1,1),CH2-1)
A4: Operating | B4: 1/0 | C4: =IF(C2>=HOTEL_OPEN_M,1,0) | D4: =IF(D2>=HOTEL_OPEN_M,1,0) | E4: =IF(E2>=HOTEL_OPEN_M,1,0) | F4: =IF(F2>=HOTEL_OPEN_M,1,0) | G4: =IF(G2>=HOTEL_OPEN_M,1,0) | H4: =IF(H2>=HOTEL_OPEN_M,1,0) | I4: =IF(I2>=HOTEL_OPEN_M,1,0) | J4: =IF(J2>=HOTEL_OPEN_M,1,0) | ... CH4: =IF(CH2>=HOTEL_OPEN_M,1,0)
A5: Operating year | B5: year | C5: =IF(C4=1,INT((C2-HOTEL_OPEN_M)/12)+1,0) | D5: =IF(D4=1,INT((D2-HOTEL_OPEN_M)/12)+1,0) | E5: =IF(E4=1,INT((E2-HOTEL_OPEN_M)/12)+1,0) | F5: =IF(F4=1,INT((F2-HOTEL_OPEN_M)/12)+1,0) | G5: =IF(G4=1,INT((G2-HOTEL_OPEN_M)/12)+1,0) | H5: =IF(H4=1,INT((H2-HOTEL_OPEN_M)/12)+1,0) | I5: =IF(I4=1,INT((I2-HOTEL_OPEN_M)/12)+1,0) | J5: =IF(J4=1,INT((J2-HOTEL_OPEN_M)/12)+1,0) | ... CH5: =IF(CH4=1,INT((CH2-HOTEL_OPEN_M)/12)+1,0)
A6: ADR | B6: $ | C6: =IF(C4=1,ADR_Y1*(1+ADR_GROWTH_PCT)^(C5-1),0) | D6: =IF(D4=1,ADR_Y1*(1+ADR_GROWTH_PCT)^(D5-1),0) | E6: =IF(E4=1,ADR_Y1*(1+ADR_GROWTH_PCT)^(E5-1),0) | F6: =IF(F4=1,ADR_Y1*(1+ADR_GROWTH_PCT)^(F5-1),0) | G6: =IF(G4=1,ADR_Y1*(1+ADR_GROWTH_PCT)^(G5-1),0) | H6: =IF(H4=1,ADR_Y1*(1+ADR_GROWTH_PCT)^(H5-1),0) | I6: =IF(I4=1,ADR_Y1*(1+ADR_GROWTH_PCT)^(I5-1),0) | J6: =IF(J4=1,ADR_Y1*(1+ADR_GROWTH_PCT)^(J5-1),0) | ... CH6: =IF(CH4=1,ADR_Y1*(1+ADR_GROWTH_PCT)^(CH5-1),0)
A7: Occupancy | B7: % | C7: =IF(C4=1,IF(C5<=1,OCC_Y1,IF(C5=2,OCC_Y2,OCC_STAB)),0) | D7: =IF(D4=1,IF(D5<=1,OCC_Y1,IF(D5=2,OCC_Y2,OCC_STAB)),0) | E7: =IF(E4=1,IF(E5<=1,OCC_Y1,IF(E5=2,OCC_Y2,OCC_STAB)),0) | F7: =IF(F4=1,IF(F5<=1,OCC_Y1,IF(F5=2,OCC_Y2,OCC_STAB)),0) | G7: =IF(G4=1,IF(G5<=1,OCC_Y1,IF(G5=2,OCC_Y2,OCC_STAB)),0) | H7: =IF(H4=1,IF(H5<=1,OCC_Y1,IF(H5=2,OCC_Y2,OCC_STAB)),0) | I7: =IF(I4=1,IF(I5<=1,OCC_Y1,IF(I5=2,OCC_Y2,OCC_STAB)),0) | J7: =IF(J4=1,IF(J5<=1,OCC_Y1,IF(J5=2,OCC_Y2,OCC_STAB)),0) | ... CH7: =IF(CH4=1,IF(CH5<=1,OCC_Y1,IF(CH5=2,OCC_Y2,OCC_STAB)),0)
A8: Days | B8: days | C8: =IF(C4=1,DAY(C3),0) | D8: =IF(D4=1,DAY(D3),0) | E8: =IF(E4=1,DAY(E3),0) | F8: =IF(F4=1,DAY(F3),0) | G8: =IF(G4=1,DAY(G3),0) | H8: =IF(H4=1,DAY(H3),0) | I8: =IF(I4=1,DAY(I3),0) | J8: =IF(J4=1,DAY(J3),0) | ... CH8: =IF(CH4=1,DAY(CH3),0)
A9: Rooms revenue | B9: $ | C9: =IF(C4=1,HOTEL_KEYS*C8*C7*C6,0) | D9: =IF(D4=1,HOTEL_KEYS*D8*D7*D6,0) | E9: =IF(E4=1,HOTEL_KEYS*E8*E7*E6,0) | F9: =IF(F4=1,HOTEL_KEYS*F8*F7*F6,0) | G9: =IF(G4=1,HOTEL_KEYS*G8*G7*G6,0) | H9: =IF(H4=1,HOTEL_KEYS*H8*H7*H6,0) | I9: =IF(I4=1,HOTEL_KEYS*I8*I7*I6,0) | J9: =IF(J4=1,HOTEL_KEYS*J8*J7*J6,0) | ... CH9: =IF(CH4=1,HOTEL_KEYS*CH8*CH7*CH6,0)
A10: Total revenue | B10: $ | C10: =C9*(1+FB_REV_PCT+OTHER_REV_PCT) | D10: =D9*(1+FB_REV_PCT+OTHER_REV_PCT) | E10: =E9*(1+FB_REV_PCT+OTHER_REV_PCT) | F10: =F9*(1+FB_REV_PCT+OTHER_REV_PCT) | G10: =G9*(1+FB_REV_PCT+OTHER_REV_PCT) | H10: =H9*(1+FB_REV_PCT+OTHER_REV_PCT) | I10: =I9*(1+FB_REV_PCT+OTHER_REV_PCT) | J10: =J9*(1+FB_REV_PCT+OTHER_REV_PCT) | ... CH10: =CH9*(1+FB_REV_PCT+OTHER_REV_PCT)
A11: Hotel NOI | B11: $ | C11: =C10*(1-HOTEL_UNDIST_PCT-HOTEL_MGMT_PCT-REPL_RESERVE_PCT) | D11: =D10*(1-HOTEL_UNDIST_PCT-HOTEL_MGMT_PCT-REPL_RESERVE_PCT) | E11: =E10*(1-HOTEL_UNDIST_PCT-HOTEL_MGMT_PCT-REPL_RESERVE_PCT) | F11: =F10*(1-HOTEL_UNDIST_PCT-HOTEL_MGMT_PCT-REPL_RESERVE_PCT) | G11: =G10*(1-HOTEL_UNDIST_PCT-HOTEL_MGMT_PCT-REPL_RESERVE_PCT) | H11: =H10*(1-HOTEL_UNDIST_PCT-HOTEL_MGMT_PCT-REPL_RESERVE_PCT) | I11: =I10*(1-HOTEL_UNDIST_PCT-HOTEL_MGMT_PCT-REPL_RESERVE_PCT) | J11: =J10*(1-HOTEL_UNDIST_PCT-HOTEL_MGMT_PCT-REPL_RESERVE_PCT) | ... CH11: =CH10*(1-HOTEL_UNDIST_PCT-HOTEL_MGMT_PCT-REPL_RESERVE_PCT)

Sheet ConstructionDebt
A1: ConstructionDebt
A2: Month | B2: index | C2: =COLUMN()-2 | D2: =COLUMN()-2 | E2: =COLUMN()-2 | F2: =COLUMN()-2 | G2: =COLUMN()-2 | H2: =COLUMN()-2 | I2: =COLUMN()-2 | J2: =COLUMN()-2 | ... CH2: =COLUMN()-2
A3: Date | B3: month-end | C3: =EOMONTH(DATE(2026,1,1),C2-1) | D3: =EOMONTH(DATE(2026,1,1),D2-1) | E3: =EOMONTH(DATE(2026,1,1),E2-1) | F3: =EOMONTH(DATE(2026,1,1),F2-1) | G3: =EOMONTH(DATE(2026,1,1),G2-1) | H3: =EOMONTH(DATE(2026,1,1),H2-1) | I3: =EOMONTH(DATE(2026,1,1),I2-1) | J3: =EOMONTH(DATE(2026,1,1),J2-1) | ... CH3: =EOMONTH(DATE(2026,1,1),CH2-1)
A4: SOFR forward | B4: % | C4: =INDEX(SOFR!$C$2:$C$85,C2) | D4: =INDEX(SOFR!$C$2:$C$85,D2) | E4: =INDEX(SOFR!$C$2:$C$85,E2) | F4: =INDEX(SOFR!$C$2:$C$85,F2) | G4: =INDEX(SOFR!$C$2:$C$85,G2) | H4: =INDEX(SOFR!$C$2:$C$85,H2) | I4: =INDEX(SOFR!$C$2:$C$85,I2) | J4: =INDEX(SOFR!$C$2:$C$85,J2) | ... CH4: =INDEX(SOFR!$C$2:$C$85,CH2)
A5: All-in rate | B5: % | C5: =MAX(SOFR_FLOOR_PCT,C4)+CT_SPREAD_PCT | D5: =MAX(SOFR_FLOOR_PCT,D4)+CT_SPREAD_PCT | E5: =MAX(SOFR_FLOOR_PCT,E4)+CT_SPREAD_PCT | F5: =MAX(SOFR_FLOOR_PCT,F4)+CT_SPREAD_PCT | G5: =MAX(SOFR_FLOOR_PCT,G4)+CT_SPREAD_PCT | H5: =MAX(SOFR_FLOOR_PCT,H4)+CT_SPREAD_PCT | I5: =MAX(SOFR_FLOOR_PCT,I4)+CT_SPREAD_PCT | J5: =MAX(SOFR_FLOOR_PCT,J4)+CT_SPREAD_PCT | ... CH5: =MAX(SOFR_FLOOR_PCT,CH4)+CT_SPREAD_PCT
A6: Budget spend | B6: $ | C6: =SpendCurve!C10 | D6: =SpendCurve!D10 | E6: =SpendCurve!E10 | F6: =SpendCurve!F10 | G6: =SpendCurve!G10 | H6: =SpendCurve!H10 | I6: =SpendCurve!I10 | J6: =SpendCurve!J10 | ... CH6: =SpendCurve!CH10
A7: Equity cash opening | B7: $ | C7: =0 | D7: =C10 | E7: =D10 | F7: =E10 | G7: =F10 | H7: =G10 | I7: =H10 | J7: =I10 | K7: =J10 | ... CH7: =CG10
A8: Equity contribution | B8: $ | C8: =IF(C2=1,SourcesUses!$C$28,0) | D8: =IF(D2=1,SourcesUses!$C$28,0) | E8: =IF(E2=1,SourcesUses!$C$28,0) | F8: =IF(F2=1,SourcesUses!$C$28,0) | G8: =IF(G2=1,SourcesUses!$C$28,0) | H8: =IF(H2=1,SourcesUses!$C$28,0) | I8: =IF(I2=1,SourcesUses!$C$28,0) | J8: =IF(J2=1,SourcesUses!$C$28,0) | ... CH8: =IF(CH2=1,SourcesUses!$C$28,0)
A9: Equity used | B9: $ | C9: =MIN(C7+C8,C6) | D9: =MIN(D7+D8,D6) | E9: =MIN(E7+E8,E6) | F9: =MIN(F7+F8,F6) | G9: =MIN(G7+G8,G6) | H9: =MIN(H7+H8,H6) | I9: =MIN(I7+I8,I6) | J9: =MIN(J7+J8,J6) | ... CH9: =MIN(CH7+CH8,CH6)
A10: Equity cash closing | B10: $ | C10: =C7+C8-C9 | D10: =D7+D8-D9 | E10: =E7+E8-E9 | F10: =F7+F8-F9 | G10: =G7+G8-G9 | H10: =H7+H8-H9 | I10: =I7+I8-I9 | J10: =J7+J8-J9 | ... CH10: =CH7+CH8-CH9
A11: Draws for spend | B11: $ | C11: =C6-C9 | D11: =D6-D9 | E11: =E6-E9 | F11: =F6-F9 | G11: =G6-G9 | H11: =H6-H9 | I11: =I6-I9 | J11: =J6-J9 | ... CH11: =CH6-CH9
A12: Debt opening balance | B12: $ | C12: =0 | D12: =C21 | E12: =D21 | F12: =E21 | G12: =F21 | H12: =G21 | I12: =H21 | J12: =I21 | K12: =J21 | ... CH12: =CG21
A13: Interest on opening balance | B13: $ | C13: =C12*(MAX(SOFR_FLOOR_PCT,INDEX(SOFR!$C$2:$C$85,C2))+CT_SPREAD_PCT)/12 | D13: =D12*(MAX(SOFR_FLOOR_PCT,INDEX(SOFR!$C$2:$C$85,D2))+CT_SPREAD_PCT)/12 | E13: =E12*(MAX(SOFR_FLOOR_PCT,INDEX(SOFR!$C$2:$C$85,E2))+CT_SPREAD_PCT)/12 | F13: =F12*(MAX(SOFR_FLOOR_PCT,INDEX(SOFR!$C$2:$C$85,F2))+CT_SPREAD_PCT)/12 | G13: =G12*(MAX(SOFR_FLOOR_PCT,INDEX(SOFR!$C$2:$C$85,G2))+CT_SPREAD_PCT)/12 | H13: =H12*(MAX(SOFR_FLOOR_PCT,INDEX(SOFR!$C$2:$C$85,H2))+CT_SPREAD_PCT)/12 | I13: =I12*(MAX(SOFR_FLOOR_PCT,INDEX(SOFR!$C$2:$C$85,I2))+CT_SPREAD_PCT)/12 | J13: =J12*(MAX(SOFR_FLOOR_PCT,INDEX(SOFR!$C$2:$C$85,J2))+CT_SPREAD_PCT)/12 | ... CH13: =CH12*(MAX(SOFR_FLOOR_PCT,INDEX(SOFR!$C$2:$C$85,CH2))+CT_SPREAD_PCT)/12
A14: Capitalized interest draw | B14: $ | C14: =C13 | D14: =D13 | E14: =E13 | F14: =F13 | G14: =G13 | H14: =H13 | I14: =I13 | J14: =J13 | ... CH14: =CH13
A15: Total draws | B15: $ | C15: =C11+C14 | D15: =D11+D14 | E15: =E11+E14 | F15: =F11+F14 | G15: =G11+G14 | H15: =H11+H14 | I15: =I11+I14 | J15: =J11+J14 | ... CH15: =CH11+CH14
A16: Balance after draws | B16: $ | C16: =C12+C15 | D16: =D12+D15 | E16: =E12+E15 | F16: =F12+F15 | G16: =G12+G15 | H16: =H12+H15 | I16: =I12+I15 | J16: =J12+J15 | ... CH16: =CH12+CH15
A17: Condo net revenue | B17: $ | C17: =CondoSellout!C16 | D17: =CondoSellout!D16 | E17: =CondoSellout!E16 | F17: =CondoSellout!F16 | G17: =CondoSellout!G16 | H17: =CondoSellout!H16 | I17: =CondoSellout!I16 | J17: =CondoSellout!J16 | ... CH17: =CondoSellout!CH16
A18: Condo repayment | B18: $ | C18: =MIN(C16,MAX(C17,0)) | D18: =MIN(D16,MAX(D17,0)) | E18: =MIN(E16,MAX(E17,0)) | F18: =MIN(F16,MAX(F17,0)) | G18: =MIN(G16,MAX(G17,0)) | H18: =MIN(H16,MAX(H17,0)) | I18: =MIN(I16,MAX(I17,0)) | J18: =MIN(J16,MAX(J17,0)) | ... CH18: =MIN(CH16,MAX(CH17,0))
A19: Permanent-loan payoff of construction balance | B19: $ | C19: =IF(C2=PERM_CONV_M,MAX(0,C16-C18),0) | D19: =IF(D2=PERM_CONV_M,MAX(0,D16-D18),0) | E19: =IF(E2=PERM_CONV_M,MAX(0,E16-E18),0) | F19: =IF(F2=PERM_CONV_M,MAX(0,F16-F18),0) | G19: =IF(G2=PERM_CONV_M,MAX(0,G16-G18),0) | H19: =IF(H2=PERM_CONV_M,MAX(0,H16-H18),0) | I19: =IF(I2=PERM_CONV_M,MAX(0,I16-I18),0) | J19: =IF(J2=PERM_CONV_M,MAX(0,J16-J18),0) | ... CH19: =IF(CH2=PERM_CONV_M,MAX(0,CH16-CH18),0)
A20: Total repayments | B20: $ | C20: =C18+C19 | D20: =D18+D19 | E20: =E18+E19 | F20: =F18+F19 | G20: =G18+G19 | H20: =H18+H19 | I20: =I18+I19 | J20: =J18+J19 | ... CH20: =CH18+CH19
A21: Debt closing balance | B21: $ | C21: =C12+C15-C20 | D21: =D12+D15-D20 | E21: =E12+E15-E20 | F21: =F12+F15-F20 | G21: =G12+G15-G20 | H21: =H12+H15-H20 | I21: =I12+I15-I20 | J21: =J12+J15-J20 | ... CH21: =CH12+CH15-CH20
A23: Audit interest gap | B23: $ | C23: =ABS(C13-C12*(MAX(SOFR_FLOOR_PCT,INDEX(SOFR!$C$2:$C$85,C2))+CT_SPREAD_PCT)/12) | D23: =ABS(D13-D12*(MAX(SOFR_FLOOR_PCT,INDEX(SOFR!$C$2:$C$85,D2))+CT_SPREAD_PCT)/12) | E23: =ABS(E13-E12*(MAX(SOFR_FLOOR_PCT,INDEX(SOFR!$C$2:$C$85,E2))+CT_SPREAD_PCT)/12) | F23: =ABS(F13-F12*(MAX(SOFR_FLOOR_PCT,INDEX(SOFR!$C$2:$C$85,F2))+CT_SPREAD_PCT)/12) | G23: =ABS(G13-G12*(MAX(SOFR_FLOOR_PCT,INDEX(SOFR!$C$2:$C$85,G2))+CT_SPREAD_PCT)/12) | H23: =ABS(H13-H12*(MAX(SOFR_FLOOR_PCT,INDEX(SOFR!$C$2:$C$85,H2))+CT_SPREAD_PCT)/12) | I23: =ABS(I13-I12*(MAX(SOFR_FLOOR_PCT,INDEX(SOFR!$C$2:$C$85,I2))+CT_SPREAD_PCT)/12) | J23: =ABS(J13-J12*(MAX(SOFR_FLOOR_PCT,INDEX(SOFR!$C$2:$C$85,J2))+CT_SPREAD_PCT)/12) | ... CH23: =ABS(CH13-CH12*(MAX(SOFR_FLOOR_PCT,INDEX(SOFR!$C$2:$C$85,CH2))+CT_SPREAD_PCT)/12)
A24: Audit roll-forward gap | B24: $ | C24: =ABS(C12-0) | D24: =ABS(D12-(C12+C15-C20)) | E24: =ABS(E12-(D12+D15-D20)) | F24: =ABS(F12-(E12+E15-E20)) | G24: =ABS(G12-(F12+F15-F20)) | H24: =ABS(H12-(G12+G15-G20)) | I24: =ABS(I12-(H12+H15-H20)) | J24: =ABS(J12-(I12+I15-I20)) | K24: =ABS(K12-(J12+J15-J20)) | ... CH24: =ABS(CH12-(CG12+CG15-CG20))

Sheet PermanentDebt
A1: PermanentDebt
A2: Month | B2: index | C2: =COLUMN()-2 | D2: =COLUMN()-2 | E2: =COLUMN()-2 | F2: =COLUMN()-2 | G2: =COLUMN()-2 | H2: =COLUMN()-2 | I2: =COLUMN()-2 | J2: =COLUMN()-2 | ... CH2: =COLUMN()-2
A3: Date | B3: month-end | C3: =EOMONTH(DATE(2026,1,1),C2-1) | D3: =EOMONTH(DATE(2026,1,1),D2-1) | E3: =EOMONTH(DATE(2026,1,1),E2-1) | F3: =EOMONTH(DATE(2026,1,1),F2-1) | G3: =EOMONTH(DATE(2026,1,1),G2-1) | H3: =EOMONTH(DATE(2026,1,1),H2-1) | I3: =EOMONTH(DATE(2026,1,1),I2-1) | J3: =EOMONTH(DATE(2026,1,1),J2-1) | ... CH3: =EOMONTH(DATE(2026,1,1),CH2-1)
A4: Permanent loan active | B4: 1/0 | C4: =IF(AND(C2>=PERM_CONV_M,C2<=EXIT_M),1,0) | D4: =IF(AND(D2>=PERM_CONV_M,D2<=EXIT_M),1,0) | E4: =IF(AND(E2>=PERM_CONV_M,E2<=EXIT_M),1,0) | F4: =IF(AND(F2>=PERM_CONV_M,F2<=EXIT_M),1,0) | G4: =IF(AND(G2>=PERM_CONV_M,G2<=EXIT_M),1,0) | H4: =IF(AND(H2>=PERM_CONV_M,H2<=EXIT_M),1,0) | I4: =IF(AND(I2>=PERM_CONV_M,I2<=EXIT_M),1,0) | J4: =IF(AND(J2>=PERM_CONV_M,J2<=EXIT_M),1,0) | ... CH4: =IF(AND(CH2>=PERM_CONV_M,CH2<=EXIT_M),1,0)
A5: Opening balance | B5: $ | C5: =IF(C2<PERM_CONV_M,0,IF(C2=PERM_CONV_M,$C$39,0)) | D5: =IF(D2<PERM_CONV_M,0,IF(D2=PERM_CONV_M,$C$39,C12)) | E5: =IF(E2<PERM_CONV_M,0,IF(E2=PERM_CONV_M,$C$39,D12)) | F5: =IF(F2<PERM_CONV_M,0,IF(F2=PERM_CONV_M,$C$39,E12)) | G5: =IF(G2<PERM_CONV_M,0,IF(G2=PERM_CONV_M,$C$39,F12)) | H5: =IF(H2<PERM_CONV_M,0,IF(H2=PERM_CONV_M,$C$39,G12)) | I5: =IF(I2<PERM_CONV_M,0,IF(I2=PERM_CONV_M,$C$39,H12)) | J5: =IF(J2<PERM_CONV_M,0,IF(J2=PERM_CONV_M,$C$39,I12)) | K5: =IF(K2<PERM_CONV_M,0,IF(K2=PERM_CONV_M,$C$39,J12)) | ... CH5: =IF(CH2<PERM_CONV_M,0,IF(CH2=PERM_CONV_M,$C$39,CG12))
A6: Interest on opening balance | B6: $ | C6: =C5*PERM_RATE_PCT/12 | D6: =D5*PERM_RATE_PCT/12 | E6: =E5*PERM_RATE_PCT/12 | F6: =F5*PERM_RATE_PCT/12 | G6: =G5*PERM_RATE_PCT/12 | H6: =H5*PERM_RATE_PCT/12 | I6: =I5*PERM_RATE_PCT/12 | J6: =J5*PERM_RATE_PCT/12 | ... CH6: =CH5*PERM_RATE_PCT/12
A7: Scheduled payment | B7: $ | C7: =IF(AND(C2>=PERM_CONV_M,C2<EXIT_M),PMT(PERM_RATE_PCT/12,PERM_AMORT_YRS*12,-$C$39),0) | D7: =IF(AND(D2>=PERM_CONV_M,D2<EXIT_M),PMT(PERM_RATE_PCT/12,PERM_AMORT_YRS*12,-$C$39),0) | E7: =IF(AND(E2>=PERM_CONV_M,E2<EXIT_M),PMT(PERM_RATE_PCT/12,PERM_AMORT_YRS*12,-$C$39),0) | F7: =IF(AND(F2>=PERM_CONV_M,F2<EXIT_M),PMT(PERM_RATE_PCT/12,PERM_AMORT_YRS*12,-$C$39),0) | G7: =IF(AND(G2>=PERM_CONV_M,G2<EXIT_M),PMT(PERM_RATE_PCT/12,PERM_AMORT_YRS*12,-$C$39),0) | H7: =IF(AND(H2>=PERM_CONV_M,H2<EXIT_M),PMT(PERM_RATE_PCT/12,PERM_AMORT_YRS*12,-$C$39),0) | I7: =IF(AND(I2>=PERM_CONV_M,I2<EXIT_M),PMT(PERM_RATE_PCT/12,PERM_AMORT_YRS*12,-$C$39),0) | J7: =IF(AND(J2>=PERM_CONV_M,J2<EXIT_M),PMT(PERM_RATE_PCT/12,PERM_AMORT_YRS*12,-$C$39),0) | ... CH7: =IF(AND(CH2>=PERM_CONV_M,CH2<EXIT_M),PMT(PERM_RATE_PCT/12,PERM_AMORT_YRS*12,-$C$39),0)
A8: Scheduled principal | B8: $ | C8: =IF(C7=0,0,C7-C6) | D8: =IF(D7=0,0,D7-D6) | E8: =IF(E7=0,0,E7-E6) | F8: =IF(F7=0,0,F7-F6) | G8: =IF(G7=0,0,G7-G6) | H8: =IF(H7=0,0,H7-H6) | I8: =IF(I7=0,0,I7-I6) | J8: =IF(J7=0,0,J7-J6) | ... CH8: =IF(CH7=0,0,CH7-CH6)
A9: Exit payoff | B9: $ | C9: =IF(C2=EXIT_M,C5,0) | D9: =IF(D2=EXIT_M,D5,0) | E9: =IF(E2=EXIT_M,E5,0) | F9: =IF(F2=EXIT_M,F5,0) | G9: =IF(G2=EXIT_M,G5,0) | H9: =IF(H2=EXIT_M,H5,0) | I9: =IF(I2=EXIT_M,I5,0) | J9: =IF(J2=EXIT_M,J5,0) | ... CH9: =IF(CH2=EXIT_M,CH5,0)
A10: Debt service excluding balloon | B10: $ | C10: =C6+C8 | D10: =D6+D8 | E10: =E6+E8 | F10: =F6+F8 | G10: =G6+G8 | H10: =H6+H8 | I10: =I6+I8 | J10: =J6+J8 | ... CH10: =CH6+CH8
A11: Construction balance repaid | B11: $ | C11: =ConstructionDebt!C19 | D11: =ConstructionDebt!D19 | E11: =ConstructionDebt!E19 | F11: =ConstructionDebt!F19 | G11: =ConstructionDebt!G19 | H11: =ConstructionDebt!H19 | I11: =ConstructionDebt!I19 | J11: =ConstructionDebt!J19 | ... CH11: =ConstructionDebt!CH19
A12: Closing balance | B12: $ | C12: =C5-C8-C9 | D12: =D5-D8-D9 | E12: =E5-E8-E9 | F12: =F5-F8-F9 | G12: =G5-G8-G9 | H12: =H5-H8-H9 | I12: =I5-I8-I9 | J12: =J5-J8-J9 | ... CH12: =CH5-CH8-CH9
A13: Net refinance proceeds | B13: $ | C13: =IF(C2=PERM_CONV_M,$C$39*(1-PERM_COSTS_PCT)-C11,0) | D13: =IF(D2=PERM_CONV_M,$C$39*(1-PERM_COSTS_PCT)-D11,0) | E13: =IF(E2=PERM_CONV_M,$C$39*(1-PERM_COSTS_PCT)-E11,0) | F13: =IF(F2=PERM_CONV_M,$C$39*(1-PERM_COSTS_PCT)-F11,0) | G13: =IF(G2=PERM_CONV_M,$C$39*(1-PERM_COSTS_PCT)-G11,0) | H13: =IF(H2=PERM_CONV_M,$C$39*(1-PERM_COSTS_PCT)-H11,0) | I13: =IF(I2=PERM_CONV_M,$C$39*(1-PERM_COSTS_PCT)-I11,0) | J13: =IF(J2=PERM_CONV_M,$C$39*(1-PERM_COSTS_PCT)-J11,0) | ... CH13: =IF(CH2=PERM_CONV_M,$C$39*(1-PERM_COSTS_PCT)-CH11,0)
A29: Sizing at conversion, on T12 NOI ending PERM_CONV_M
A30: Hotel T12 NOI at conversion | B30: $ | C30: =SUM(INDEX(HotelProForma!C11:CH11,PERM_CONV_M-11):INDEX(HotelProForma!C11:CH11,PERM_CONV_M))
A31: Retail T12 NOI at conversion | B31: $ | C31: =SUM(INDEX(RetailProForma!C12:CH12,PERM_CONV_M-11):INDEX(RetailProForma!C12:CH12,PERM_CONV_M))
A32: Combined T12 NOI | B32: $ | C32: =C30+C31
A33: Hotel value at conversion | B33: $ | C33: =C30/HOTEL_CAP
A34: Retail value at conversion | B34: $ | C34: =C31/RETAIL_CAP
A35: LTV size | B35: $ | C35: =PERM_LTV*(C33+C34) | D35: Proceeds are the minimum of the LTV, DSCR, and debt-yield sizes.
A36: PMT factor | B36: $ per $1 | C36: =PMT(PERM_RATE_PCT/12,PERM_AMORT_YRS*12,-1)
A37: DSCR size | B37: $ | C37: =(C32/PERM_DSCR)/C36
A38: Debt-yield size | B38: $ | C38: =C32/PERM_DY
A39: Permanent proceeds | B39: $ | C39: =MIN(C35,C37,C38)

Sheet HotelValuation
A1: HotelValuation
A2: Month | B2: index | C2: =COLUMN()-2 | D2: =COLUMN()-2 | E2: =COLUMN()-2 | F2: =COLUMN()-2 | G2: =COLUMN()-2 | H2: =COLUMN()-2 | I2: =COLUMN()-2 | J2: =COLUMN()-2 | ... CH2: =COLUMN()-2
A3: Date | B3: month-end | C3: =EOMONTH(DATE(2026,1,1),C2-1) | D3: =EOMONTH(DATE(2026,1,1),D2-1) | E3: =EOMONTH(DATE(2026,1,1),E2-1) | F3: =EOMONTH(DATE(2026,1,1),F2-1) | G3: =EOMONTH(DATE(2026,1,1),G2-1) | H3: =EOMONTH(DATE(2026,1,1),H2-1) | I3: =EOMONTH(DATE(2026,1,1),I2-1) | J3: =EOMONTH(DATE(2026,1,1),J2-1) | ... CH3: =EOMONTH(DATE(2026,1,1),CH2-1)
A4: Hotel NOI | B4: $ | C4: =HotelProForma!C11 | D4: =HotelProForma!D11 | E4: =HotelProForma!E11 | F4: =HotelProForma!F11 | G4: =HotelProForma!G11 | H4: =HotelProForma!H11 | I4: =HotelProForma!I11 | J4: =HotelProForma!J11 | ... CH4: =HotelProForma!CH11
A6: T12 NOI at exit | B6: $ | C6: =SUM(INDEX(C4:CH4,EXIT_M-11):INDEX(C4:CH4,EXIT_M)) | D6: Trailing 12 months ending EXIT_M.
A7: Hotel value | B7: $ | C7: =C6/HOTEL_CAP | D7: T12 NOI divided by HOTEL_CAP. No condo cap rate on this sheet.
A9: T12 build-up
A10: Trailing month 1 | B10: month | C10: =INDEX($C$2:$CH$2,EXIT_M-12+1) | D10: =INDEX($C$4:$CH$4,EXIT_M-12+1)
A11: Trailing month 2 | B11: month | C11: =INDEX($C$2:$CH$2,EXIT_M-12+2) | D11: =INDEX($C$4:$CH$4,EXIT_M-12+2)
A12: Trailing month 3 | B12: month | C12: =INDEX($C$2:$CH$2,EXIT_M-12+3) | D12: =INDEX($C$4:$CH$4,EXIT_M-12+3)
A13: Trailing month 4 | B13: month | C13: =INDEX($C$2:$CH$2,EXIT_M-12+4) | D13: =INDEX($C$4:$CH$4,EXIT_M-12+4)
A14: Trailing month 5 | B14: month | C14: =INDEX($C$2:$CH$2,EXIT_M-12+5) | D14: =INDEX($C$4:$CH$4,EXIT_M-12+5)
A15: Trailing month 6 | B15: month | C15: =INDEX($C$2:$CH$2,EXIT_M-12+6) | D15: =INDEX($C$4:$CH$4,EXIT_M-12+6)
A16: Trailing month 7 | B16: month | C16: =INDEX($C$2:$CH$2,EXIT_M-12+7) | D16: =INDEX($C$4:$CH$4,EXIT_M-12+7)
A17: Trailing month 8 | B17: month | C17: =INDEX($C$2:$CH$2,EXIT_M-12+8) | D17: =INDEX($C$4:$CH$4,EXIT_M-12+8)
A18: Trailing month 9 | B18: month | C18: =INDEX($C$2:$CH$2,EXIT_M-12+9) | D18: =INDEX($C$4:$CH$4,EXIT_M-12+9)
A19: Trailing month 10 | B19: month | C19: =INDEX($C$2:$CH$2,EXIT_M-12+10) | D19: =INDEX($C$4:$CH$4,EXIT_M-12+10)
A20: Trailing month 11 | B20: month | C20: =INDEX($C$2:$CH$2,EXIT_M-12+11) | D20: =INDEX($C$4:$CH$4,EXIT_M-12+11)
A21: Trailing month 12 | B21: month | C21: =INDEX($C$2:$CH$2,EXIT_M-12+12) | D21: =INDEX($C$4:$CH$4,EXIT_M-12+12)
A22: T12 build-up sum | B22: $ | C22: =SUM(D10:D21)
A23: Build-up minus T12 | B23: $ | C23: =C22-C6

Sheet RetailValuation
A1: RetailValuation
A2: Month | B2: index | C2: =COLUMN()-2 | D2: =COLUMN()-2 | E2: =COLUMN()-2 | F2: =COLUMN()-2 | G2: =COLUMN()-2 | H2: =COLUMN()-2 | I2: =COLUMN()-2 | J2: =COLUMN()-2 | ... CH2: =COLUMN()-2
A3: Date | B3: month-end | C3: =EOMONTH(DATE(2026,1,1),C2-1) | D3: =EOMONTH(DATE(2026,1,1),D2-1) | E3: =EOMONTH(DATE(2026,1,1),E2-1) | F3: =EOMONTH(DATE(2026,1,1),F2-1) | G3: =EOMONTH(DATE(2026,1,1),G2-1) | H3: =EOMONTH(DATE(2026,1,1),H2-1) | I3: =EOMONTH(DATE(2026,1,1),I2-1) | J3: =EOMONTH(DATE(2026,1,1),J2-1) | ... CH3: =EOMONTH(DATE(2026,1,1),CH2-1)
A4: Retail NOI | B4: $ | C4: =RetailProForma!C12 | D4: =RetailProForma!D12 | E4: =RetailProForma!E12 | F4: =RetailProForma!F12 | G4: =RetailProForma!G12 | H4: =RetailProForma!H12 | I4: =RetailProForma!I12 | J4: =RetailProForma!J12 | ... CH4: =RetailProForma!CH12
A6: T12 NOI at exit | B6: $ | C6: =SUM(INDEX(C4:CH4,EXIT_M-11):INDEX(C4:CH4,EXIT_M)) | D6: Trailing 12 months ending EXIT_M.
A7: Retail value | B7: $ | C7: =C6/RETAIL_CAP | D7: T12 NOI divided by RETAIL_CAP. No condo cap rate on this sheet.
A9: T12 build-up
A10: Trailing month 1 | B10: month | C10: =INDEX($C$2:$CH$2,EXIT_M-12+1) | D10: =INDEX($C$4:$CH$4,EXIT_M-12+1)
A11: Trailing month 2 | B11: month | C11: =INDEX($C$2:$CH$2,EXIT_M-12+2) | D11: =INDEX($C$4:$CH$4,EXIT_M-12+2)
A12: Trailing month 3 | B12: month | C12: =INDEX($C$2:$CH$2,EXIT_M-12+3) | D12: =INDEX($C$4:$CH$4,EXIT_M-12+3)
A13: Trailing month 4 | B13: month | C13: =INDEX($C$2:$CH$2,EXIT_M-12+4) | D13: =INDEX($C$4:$CH$4,EXIT_M-12+4)
A14: Trailing month 5 | B14: month | C14: =INDEX($C$2:$CH$2,EXIT_M-12+5) | D14: =INDEX($C$4:$CH$4,EXIT_M-12+5)
A15: Trailing month 6 | B15: month | C15: =INDEX($C$2:$CH$2,EXIT_M-12+6) | D15: =INDEX($C$4:$CH$4,EXIT_M-12+6)
A16: Trailing month 7 | B16: month | C16: =INDEX($C$2:$CH$2,EXIT_M-12+7) | D16: =INDEX($C$4:$CH$4,EXIT_M-12+7)
A17: Trailing month 8 | B17: month | C17: =INDEX($C$2:$CH$2,EXIT_M-12+8) | D17: =INDEX($C$4:$CH$4,EXIT_M-12+8)
A18: Trailing month 9 | B18: month | C18: =INDEX($C$2:$CH$2,EXIT_M-12+9) | D18: =INDEX($C$4:$CH$4,EXIT_M-12+9)
A19: Trailing month 10 | B19: month | C19: =INDEX($C$2:$CH$2,EXIT_M-12+10) | D19: =INDEX($C$4:$CH$4,EXIT_M-12+10)
A20: Trailing month 11 | B20: month | C20: =INDEX($C$2:$CH$2,EXIT_M-12+11) | D20: =INDEX($C$4:$CH$4,EXIT_M-12+11)
A21: Trailing month 12 | B21: month | C21: =INDEX($C$2:$CH$2,EXIT_M-12+12) | D21: =INDEX($C$4:$CH$4,EXIT_M-12+12)
A22: T12 build-up sum | B22: $ | C22: =SUM(D10:D21)
A23: Build-up minus T12 | B23: $ | C23: =C22-C6

Sheet ProjectCF
A1: ProjectCF
A2: Month | B2: index | C2: =COLUMN()-2 | D2: =COLUMN()-2 | E2: =COLUMN()-2 | F2: =COLUMN()-2 | G2: =COLUMN()-2 | H2: =COLUMN()-2 | I2: =COLUMN()-2 | J2: =COLUMN()-2 | ... CH2: =COLUMN()-2
A3: Date | B3: month-end | C3: =EOMONTH(DATE(2026,1,1),C2-1) | D3: =EOMONTH(DATE(2026,1,1),D2-1) | E3: =EOMONTH(DATE(2026,1,1),E2-1) | F3: =EOMONTH(DATE(2026,1,1),F2-1) | G3: =EOMONTH(DATE(2026,1,1),G2-1) | H3: =EOMONTH(DATE(2026,1,1),H2-1) | I3: =EOMONTH(DATE(2026,1,1),I2-1) | J3: =EOMONTH(DATE(2026,1,1),J2-1) | ... CH3: =EOMONTH(DATE(2026,1,1),CH2-1)
A4: Condo net revenue | B4: $ | C4: =CondoSellout!C16 | D4: =CondoSellout!D16 | E4: =CondoSellout!E16 | F4: =CondoSellout!F16 | G4: =CondoSellout!G16 | H4: =CondoSellout!H16 | I4: =CondoSellout!I16 | J4: =CondoSellout!J16 | ... CH4: =CondoSellout!CH16
A5: Condo applied to construction debt | B5: $ | C5: =ConstructionDebt!C18 | D5: =ConstructionDebt!D18 | E5: =ConstructionDebt!E18 | F5: =ConstructionDebt!F18 | G5: =ConstructionDebt!G18 | H5: =ConstructionDebt!H18 | I5: =ConstructionDebt!I18 | J5: =ConstructionDebt!J18 | ... CH5: =ConstructionDebt!CH18
A6: Condo net after construction paydown | B6: $ | C6: =C4-C5 | D6: =D4-D5 | E6: =E4-E5 | F6: =F4-F5 | G6: =G4-G5 | H6: =H4-H5 | I6: =I4-I5 | J6: =J4-J5 | ... CH6: =CH4-CH5
A7: Hotel NOI | B7: $ | C7: =HotelProForma!C11 | D7: =HotelProForma!D11 | E7: =HotelProForma!E11 | F7: =HotelProForma!F11 | G7: =HotelProForma!G11 | H7: =HotelProForma!H11 | I7: =HotelProForma!I11 | J7: =HotelProForma!J11 | ... CH7: =HotelProForma!CH11
A8: Retail NOI | B8: $ | C8: =RetailProForma!C12 | D8: =RetailProForma!D12 | E8: =RetailProForma!E12 | F8: =RetailProForma!F12 | G8: =RetailProForma!G12 | H8: =RetailProForma!H12 | I8: =RetailProForma!I12 | J8: =RetailProForma!J12 | ... CH8: =RetailProForma!CH12
A9: Permanent debt service | B9: $ | C9: =PermanentDebt!C10 | D9: =PermanentDebt!D10 | E9: =PermanentDebt!E10 | F9: =PermanentDebt!F10 | G9: =PermanentDebt!G10 | H9: =PermanentDebt!H10 | I9: =PermanentDebt!I10 | J9: =PermanentDebt!J10 | ... CH9: =PermanentDebt!CH10
A10: Refinance net proceeds | B10: $ | C10: =PermanentDebt!C13 | D10: =PermanentDebt!D13 | E10: =PermanentDebt!E13 | F10: =PermanentDebt!F13 | G10: =PermanentDebt!G13 | H10: =PermanentDebt!H13 | I10: =PermanentDebt!I13 | J10: =PermanentDebt!J13 | ... CH10: =PermanentDebt!CH13
A11: Terminal net proceeds | B11: $ | C11: =IF(C2=EXIT_M,(HotelValuation!$C$7+RetailValuation!$C$7)*(1-SELL_COST_PCT)-PermanentDebt!C9,0) | D11: =IF(D2=EXIT_M,(HotelValuation!$C$7+RetailValuation!$C$7)*(1-SELL_COST_PCT)-PermanentDebt!D9,0) | E11: =IF(E2=EXIT_M,(HotelValuation!$C$7+RetailValuation!$C$7)*(1-SELL_COST_PCT)-PermanentDebt!E9,0) | F11: =IF(F2=EXIT_M,(HotelValuation!$C$7+RetailValuation!$C$7)*(1-SELL_COST_PCT)-PermanentDebt!F9,0) | G11: =IF(G2=EXIT_M,(HotelValuation!$C$7+RetailValuation!$C$7)*(1-SELL_COST_PCT)-PermanentDebt!G9,0) | H11: =IF(H2=EXIT_M,(HotelValuation!$C$7+RetailValuation!$C$7)*(1-SELL_COST_PCT)-PermanentDebt!H9,0) | I11: =IF(I2=EXIT_M,(HotelValuation!$C$7+RetailValuation!$C$7)*(1-SELL_COST_PCT)-PermanentDebt!I9,0) | J11: =IF(J2=EXIT_M,(HotelValuation!$C$7+RetailValuation!$C$7)*(1-SELL_COST_PCT)-PermanentDebt!J9,0) | ... CH11: =IF(CH2=EXIT_M,(HotelValuation!$C$7+RetailValuation!$C$7)*(1-SELL_COST_PCT)-PermanentDebt!CH9,0)
A12: Distributable cash | B12: $ | C12: =C6+C7+C8-C9+C10+C11 | D12: =D6+D7+D8-D9+D10+D11 | E12: =E6+E7+E8-E9+E10+E11 | F12: =F6+F7+F8-F9+F10+F11 | G12: =G6+G7+G8-G9+G10+G11 | H12: =H6+H7+H8-H9+H10+H11 | I12: =I6+I7+I8-I9+I10+I11 | J12: =J6+J7+J8-J9+J10+J11 | ... CH12: =CH6+CH7+CH8-CH9+CH10+CH11
A13: Equity contribution | B13: $ | C13: =ConstructionDebt!C8 | D13: =ConstructionDebt!D8 | E13: =ConstructionDebt!E8 | F13: =ConstructionDebt!F8 | G13: =ConstructionDebt!G8 | H13: =ConstructionDebt!H8 | I13: =ConstructionDebt!I8 | J13: =ConstructionDebt!J8 | ... CH13: =ConstructionDebt!CH8
A14: Waterfall tier 1 | B14: $ | C14: =Waterfall!C9 | D14: =Waterfall!D9 | E14: =Waterfall!E9 | F14: =Waterfall!F9 | G14: =Waterfall!G9 | H14: =Waterfall!H9 | I14: =Waterfall!I9 | J14: =Waterfall!J9 | ... CH14: =Waterfall!CH9
A15: Waterfall tier 2 | B15: $ | C15: =Waterfall!C20 | D15: =Waterfall!D20 | E15: =Waterfall!E20 | F15: =Waterfall!F20 | G15: =Waterfall!G20 | H15: =Waterfall!H20 | I15: =Waterfall!I20 | J15: =Waterfall!J20 | ... CH15: =Waterfall!CH20
A16: Waterfall tier 3 | B16: $ | C16: =Waterfall!C28 | D16: =Waterfall!D28 | E16: =Waterfall!E28 | F16: =Waterfall!F28 | G16: =Waterfall!G28 | H16: =Waterfall!H28 | I16: =Waterfall!I28 | J16: =Waterfall!J28 | ... CH16: =Waterfall!CH28
A17: Waterfall tier 4 | B17: $ | C17: =Waterfall!C33 | D17: =Waterfall!D33 | E17: =Waterfall!E33 | F17: =Waterfall!F33 | G17: =Waterfall!G33 | H17: =Waterfall!H33 | I17: =Waterfall!I33 | J17: =Waterfall!J33 | ... CH17: =Waterfall!CH33
A18: Retained cash | B18: $ | C18: =C12-(C14+C15+C16+C17) | D18: =D12-(D14+D15+D16+D17) | E18: =E12-(E14+E15+E16+E17) | F18: =F12-(F14+F15+F16+F17) | G18: =G12-(G14+G15+G16+G17) | H18: =H12-(H14+H15+H16+H17) | I18: =I12-(I14+I15+I16+I17) | J18: =J12-(J14+J15+J16+J17) | ... CH18: =CH12-(CH14+CH15+CH16+CH17)

Sheet Waterfall
A1: Waterfall
A2: Month | B2: index | C2: =COLUMN()-2 | D2: =COLUMN()-2 | E2: =COLUMN()-2 | F2: =COLUMN()-2 | G2: =COLUMN()-2 | H2: =COLUMN()-2 | I2: =COLUMN()-2 | J2: =COLUMN()-2 | ... CH2: =COLUMN()-2
A3: Date | B3: month-end | C3: =EOMONTH(DATE(2026,1,1),C2-1) | D3: =EOMONTH(DATE(2026,1,1),D2-1) | E3: =EOMONTH(DATE(2026,1,1),E2-1) | F3: =EOMONTH(DATE(2026,1,1),F2-1) | G3: =EOMONTH(DATE(2026,1,1),G2-1) | H3: =EOMONTH(DATE(2026,1,1),H2-1) | I3: =EOMONTH(DATE(2026,1,1),I2-1) | J3: =EOMONTH(DATE(2026,1,1),J2-1) | ... CH3: =EOMONTH(DATE(2026,1,1),CH2-1)
A4: Distributable cash | B4: $ | C4: =ProjectCF!C12 | D4: =ProjectCF!D12 | E4: =ProjectCF!E12 | F4: =ProjectCF!F12 | G4: =ProjectCF!G12 | H4: =ProjectCF!H12 | I4: =ProjectCF!I12 | J4: =ProjectCF!J12 | ... CH4: =ProjectCF!CH12
A5: Unreturned LP capital opening | B5: $ | C5: =SourcesUses!$C$31 | D5: =C13 | E5: =D13 | F5: =E13 | G5: =F13 | H5: =G13 | I5: =H13 | J5: =I13 | K5: =J13 | ... CH5: =CG13
A6: Unpaid preferred opening | B6: $ | C6: =0 | D6: =C14 | E6: =D14 | F6: =E14 | G6: =F14 | H6: =G14 | I6: =H14 | J6: =I14 | K6: =J14 | ... CH6: =CG14
A7: Preferred accrual | B7: $ | C7: =(C5+C6)*PREF_PCT/12 | D7: =(D5+D6)*PREF_PCT/12 | E7: =(E5+E6)*PREF_PCT/12 | F7: =(F5+F6)*PREF_PCT/12 | G7: =(G5+G6)*PREF_PCT/12 | H7: =(H5+H6)*PREF_PCT/12 | I7: =(I5+I6)*PREF_PCT/12 | J7: =(J5+J6)*PREF_PCT/12 | ... CH7: =(CH5+CH6)*PREF_PCT/12
A8: Tier 1 unpaid hurdle | B8: $ | C8: =C5+C6+C7 | D8: =D5+D6+D7 | E8: =E5+E6+E7 | F8: =F5+F6+F7 | G8: =G5+G6+G7 | H8: =H5+H6+H7 | I8: =I5+I6+I7 | J8: =J5+J6+J7 | ... CH8: =CH5+CH6+CH7
A9: Tier 1 to LP | B9: $ | C9: =IF(C4<0,C4,MIN(MAX(C4,0),MAX(0,C8))) | D9: =IF(D4<0,D4,MIN(MAX(D4,0),MAX(0,D8))) | E9: =IF(E4<0,E4,MIN(MAX(E4,0),MAX(0,E8))) | F9: =IF(F4<0,F4,MIN(MAX(F4,0),MAX(0,F8))) | G9: =IF(G4<0,G4,MIN(MAX(G4,0),MAX(0,G8))) | H9: =IF(H4<0,H4,MIN(MAX(H4,0),MAX(0,H8))) | I9: =IF(I4<0,I4,MIN(MAX(I4,0),MAX(0,I8))) | J9: =IF(J4<0,J4,MIN(MAX(J4,0),MAX(0,J8))) | ... CH9: =IF(CH4<0,CH4,MIN(MAX(CH4,0),MAX(0,CH8)))
A10: Cash after tier 1 | B10: $ | C10: =C4-C9 | D10: =D4-D9 | E10: =E4-E9 | F10: =F4-F9 | G10: =G4-G9 | H10: =H4-H9 | I10: =I4-I9 | J10: =J4-J9 | ... CH10: =CH4-CH9
A11: Preferred paid | B11: $ | C11: =MIN(MAX(C9,0),C6+C7) | D11: =MIN(MAX(D9,0),D6+D7) | E11: =MIN(MAX(E9,0),E6+E7) | F11: =MIN(MAX(F9,0),F6+F7) | G11: =MIN(MAX(G9,0),G6+G7) | H11: =MIN(MAX(H9,0),H6+H7) | I11: =MIN(MAX(I9,0),I6+I7) | J11: =MIN(MAX(J9,0),J6+J7) | ... CH11: =MIN(MAX(CH9,0),CH6+CH7)
A12: LP capital returned | B12: $ | C12: =MAX(C9,0)-C11 | D12: =MAX(D9,0)-D11 | E12: =MAX(E9,0)-E11 | F12: =MAX(F9,0)-F11 | G12: =MAX(G9,0)-G11 | H12: =MAX(H9,0)-H11 | I12: =MAX(I9,0)-I11 | J12: =MAX(J9,0)-J11 | ... CH12: =MAX(CH9,0)-CH11
A13: Unreturned LP capital closing | B13: $ | C13: =C5-C12 | D13: =D5-D12 | E13: =E5-E12 | F13: =F5-F12 | G13: =G5-G12 | H13: =H5-H12 | I13: =I5-I12 | J13: =J5-J12 | ... CH13: =CH5-CH12
A14: Unpaid preferred closing | B14: $ | C14: =C6+C7-C11 | D14: =D6+D7-D11 | E14: =E6+E7-E11 | F14: =F6+F7-F11 | G14: =G6+G7-G11 | H14: =H6+H7-H11 | I14: =I6+I7-I11 | J14: =J6+J7-J11 | ... CH14: =CH6+CH7-CH11
A15: Tier 1 complete | B15: 1/0 | C15: =IF(C8-MAX(C9,0)<=0.01,1,0) | D15: =IF(D8-MAX(D9,0)<=0.01,1,0) | E15: =IF(E8-MAX(E9,0)<=0.01,1,0) | F15: =IF(F8-MAX(F9,0)<=0.01,1,0) | G15: =IF(G8-MAX(G9,0)<=0.01,1,0) | H15: =IF(H8-MAX(H9,0)<=0.01,1,0) | I15: =IF(I8-MAX(I9,0)<=0.01,1,0) | J15: =IF(J8-MAX(J9,0)<=0.01,1,0) | ... CH15: =IF(CH8-MAX(CH9,0)<=0.01,1,0)
A16: Cumulative preferred paid | B16: $ | C16: =C11 | D16: =C16+D11 | E16: =D16+E11 | F16: =E16+F11 | G16: =F16+G11 | H16: =G16+H11 | I16: =H16+I11 | J16: =I16+J11 | K16: =J16+K11 | ... CH16: =CG16+CH11
A17: Tier 2 target | B17: $ | C17: =IF(C15=1,CATCHUP_PCT/(1-CATCHUP_PCT)*C16,0) | D17: =IF(D15=1,CATCHUP_PCT/(1-CATCHUP_PCT)*D16,0) | E17: =IF(E15=1,CATCHUP_PCT/(1-CATCHUP_PCT)*E16,0) | F17: =IF(F15=1,CATCHUP_PCT/(1-CATCHUP_PCT)*F16,0) | G17: =IF(G15=1,CATCHUP_PCT/(1-CATCHUP_PCT)*G16,0) | H17: =IF(H15=1,CATCHUP_PCT/(1-CATCHUP_PCT)*H16,0) | I17: =IF(I15=1,CATCHUP_PCT/(1-CATCHUP_PCT)*I16,0) | J17: =IF(J15=1,CATCHUP_PCT/(1-CATCHUP_PCT)*J16,0) | ... CH17: =IF(CH15=1,CATCHUP_PCT/(1-CATCHUP_PCT)*CH16,0)
A18: Tier 2 previously paid | B18: $ | C18: =0 | D18: =C21 | E18: =D21 | F18: =E21 | G18: =F21 | H18: =G21 | I18: =H21 | J18: =I21 | K18: =J21 | ... CH18: =CG21
A19: Tier 2 remaining | B19: $ | C19: =MAX(0,C17-C18) | D19: =MAX(0,D17-D18) | E19: =MAX(0,E17-E18) | F19: =MAX(0,F17-F18) | G19: =MAX(0,G17-G18) | H19: =MAX(0,H17-H18) | I19: =MAX(0,I17-I18) | J19: =MAX(0,J17-J18) | ... CH19: =MAX(0,CH17-CH18)
A20: Tier 2 to GP | B20: $ | C20: =IF(C15=1,MIN(MAX(C10,0),C19),0) | D20: =IF(D15=1,MIN(MAX(D10,0),D19),0) | E20: =IF(E15=1,MIN(MAX(E10,0),E19),0) | F20: =IF(F15=1,MIN(MAX(F10,0),F19),0) | G20: =IF(G15=1,MIN(MAX(G10,0),G19),0) | H20: =IF(H15=1,MIN(MAX(H10,0),H19),0) | I20: =IF(I15=1,MIN(MAX(I10,0),I19),0) | J20: =IF(J15=1,MIN(MAX(J10,0),J19),0) | ... CH20: =IF(CH15=1,MIN(MAX(CH10,0),CH19),0)
A21: Tier 2 cumulative | B21: $ | C21: =C18+C20 | D21: =D18+D20 | E21: =E18+E20 | F21: =F18+F20 | G21: =G18+G20 | H21: =H18+H20 | I21: =I18+I20 | J21: =J18+J20 | ... CH21: =CH18+CH20
A22: Tier 2 complete | B22: 1/0 | C22: =IF(AND(C15=1,C17-C21<=0.01),1,0) | D22: =IF(AND(D15=1,D17-D21<=0.01),1,0) | E22: =IF(AND(E15=1,E17-E21<=0.01),1,0) | F22: =IF(AND(F15=1,F17-F21<=0.01),1,0) | G22: =IF(AND(G15=1,G17-G21<=0.01),1,0) | H22: =IF(AND(H15=1,H17-H21<=0.01),1,0) | I22: =IF(AND(I15=1,I17-I21<=0.01),1,0) | J22: =IF(AND(J15=1,J17-J21<=0.01),1,0) | ... CH22: =IF(AND(CH15=1,CH17-CH21<=0.01),1,0)
A23: Tier 3 LP accrual gate | B23: $ | C23: =SourcesUses!$C$31*(1+T3_ACCRUAL_PCT/12)^C2 | D23: =SourcesUses!$C$31*(1+T3_ACCRUAL_PCT/12)^D2 | E23: =SourcesUses!$C$31*(1+T3_ACCRUAL_PCT/12)^E2 | F23: =SourcesUses!$C$31*(1+T3_ACCRUAL_PCT/12)^F2 | G23: =SourcesUses!$C$31*(1+T3_ACCRUAL_PCT/12)^G2 | H23: =SourcesUses!$C$31*(1+T3_ACCRUAL_PCT/12)^H2 | I23: =SourcesUses!$C$31*(1+T3_ACCRUAL_PCT/12)^I2 | J23: =SourcesUses!$C$31*(1+T3_ACCRUAL_PCT/12)^J2 | ... CH23: =SourcesUses!$C$31*(1+T3_ACCRUAL_PCT/12)^CH2
A24: LP distributions before tier 3 | B24: $ | C24: =C9 | D24: =C39+D9 | E24: =D39+E9 | F24: =E39+F9 | G24: =F39+G9 | H24: =G39+H9 | I24: =H39+I9 | J24: =I39+J9 | K24: =J39+K9 | ... CH24: =CG39+CH9
A25: Tier 3 LP gap | B25: $ | C25: =MAX(0,C23-C24) | D25: =MAX(0,D23-D24) | E25: =MAX(0,E23-E24) | F25: =MAX(0,F23-F24) | G25: =MAX(0,G23-G24) | H25: =MAX(0,H23-H24) | I25: =MAX(0,I23-I24) | J25: =MAX(0,J23-J24) | ... CH25: =MAX(0,CH23-CH24)
A26: Tier 3 cash to close the gap | B26: $ | C26: =IF(T3_LP_SPLIT<=0,0,C25/T3_LP_SPLIT) | D26: =IF(T3_LP_SPLIT<=0,0,D25/T3_LP_SPLIT) | E26: =IF(T3_LP_SPLIT<=0,0,E25/T3_LP_SPLIT) | F26: =IF(T3_LP_SPLIT<=0,0,F25/T3_LP_SPLIT) | G26: =IF(T3_LP_SPLIT<=0,0,G25/T3_LP_SPLIT) | H26: =IF(T3_LP_SPLIT<=0,0,H25/T3_LP_SPLIT) | I26: =IF(T3_LP_SPLIT<=0,0,I25/T3_LP_SPLIT) | J26: =IF(T3_LP_SPLIT<=0,0,J25/T3_LP_SPLIT) | ... CH26: =IF(T3_LP_SPLIT<=0,0,CH25/T3_LP_SPLIT)
A27: Tier 4 already open | B27: 1/0 | C27: =0 | D27: =C32 | E27: =D32 | F27: =E32 | G27: =F32 | H27: =G32 | I27: =H32 | J27: =I32 | K27: =J32 | ... CH27: =CG32
A28: Tier 3 distribution | B28: $ | C28: =IF(C27=1,0,IF(AND(C22=1,C25>0.01),MIN(MAX(C10-C20,0),C26),0)) | D28: =IF(D27=1,0,IF(AND(D22=1,D25>0.01),MIN(MAX(D10-D20,0),D26),0)) | E28: =IF(E27=1,0,IF(AND(E22=1,E25>0.01),MIN(MAX(E10-E20,0),E26),0)) | F28: =IF(F27=1,0,IF(AND(F22=1,F25>0.01),MIN(MAX(F10-F20,0),F26),0)) | G28: =IF(G27=1,0,IF(AND(G22=1,G25>0.01),MIN(MAX(G10-G20,0),G26),0)) | H28: =IF(H27=1,0,IF(AND(H22=1,H25>0.01),MIN(MAX(H10-H20,0),H26),0)) | I28: =IF(I27=1,0,IF(AND(I22=1,I25>0.01),MIN(MAX(I10-I20,0),I26),0)) | J28: =IF(J27=1,0,IF(AND(J22=1,J25>0.01),MIN(MAX(J10-J20,0),J26),0)) | ... CH28: =IF(CH27=1,0,IF(AND(CH22=1,CH25>0.01),MIN(MAX(CH10-CH20,0),CH26),0))
A29: Tier 3 to LP | B29: $ | C29: =C28*T3_LP_SPLIT | D29: =D28*T3_LP_SPLIT | E29: =E28*T3_LP_SPLIT | F29: =F28*T3_LP_SPLIT | G29: =G28*T3_LP_SPLIT | H29: =H28*T3_LP_SPLIT | I29: =I28*T3_LP_SPLIT | J29: =J28*T3_LP_SPLIT | ... CH29: =CH28*T3_LP_SPLIT
A30: Tier 3 to GP | B30: $ | C30: =C28*(1-T3_LP_SPLIT) | D30: =D28*(1-T3_LP_SPLIT) | E30: =E28*(1-T3_LP_SPLIT) | F30: =F28*(1-T3_LP_SPLIT) | G30: =G28*(1-T3_LP_SPLIT) | H30: =H28*(1-T3_LP_SPLIT) | I30: =I28*(1-T3_LP_SPLIT) | J30: =J28*(1-T3_LP_SPLIT) | ... CH30: =CH28*(1-T3_LP_SPLIT)
A31: Tier 3 gate met this month | B31: 1/0 | C31: =IF(AND(C22=1,C24+C29+0.01>=C23),1,0) | D31: =IF(AND(D22=1,D24+D29+0.01>=D23),1,0) | E31: =IF(AND(E22=1,E24+E29+0.01>=E23),1,0) | F31: =IF(AND(F22=1,F24+F29+0.01>=F23),1,0) | G31: =IF(AND(G22=1,G24+G29+0.01>=G23),1,0) | H31: =IF(AND(H22=1,H24+H29+0.01>=H23),1,0) | I31: =IF(AND(I22=1,I24+I29+0.01>=I23),1,0) | J31: =IF(AND(J22=1,J24+J29+0.01>=J23),1,0) | ... CH31: =IF(AND(CH22=1,CH24+CH29+0.01>=CH23),1,0)
A32: Tier 4 open | B32: 1/0 | C32: =IF(OR(C27=1,C31=1),1,0) | D32: =IF(OR(D27=1,D31=1),1,0) | E32: =IF(OR(E27=1,E31=1),1,0) | F32: =IF(OR(F27=1,F31=1),1,0) | G32: =IF(OR(G27=1,G31=1),1,0) | H32: =IF(OR(H27=1,H31=1),1,0) | I32: =IF(OR(I27=1,I31=1),1,0) | J32: =IF(OR(J27=1,J31=1),1,0) | ... CH32: =IF(OR(CH27=1,CH31=1),1,0)
A33: Tier 4 distribution | B33: $ | C33: =C4-C9-C20-C28 | D33: =D4-D9-D20-D28 | E33: =E4-E9-E20-E28 | F33: =F4-F9-F20-F28 | G33: =G4-G9-G20-G28 | H33: =H4-H9-H20-H28 | I33: =I4-I9-I20-I28 | J33: =J4-J9-J20-J28 | ... CH33: =CH4-CH9-CH20-CH28
A34: Tier 4 to LP | B34: $ | C34: =C33*T4_LP_SPLIT | D34: =D33*T4_LP_SPLIT | E34: =E33*T4_LP_SPLIT | F34: =F33*T4_LP_SPLIT | G34: =G33*T4_LP_SPLIT | H34: =H33*T4_LP_SPLIT | I34: =I33*T4_LP_SPLIT | J34: =J33*T4_LP_SPLIT | ... CH34: =CH33*T4_LP_SPLIT
A35: Tier 4 to GP | B35: $ | C35: =C33*(1-T4_LP_SPLIT) | D35: =D33*(1-T4_LP_SPLIT) | E35: =E33*(1-T4_LP_SPLIT) | F35: =F33*(1-T4_LP_SPLIT) | G35: =G33*(1-T4_LP_SPLIT) | H35: =H33*(1-T4_LP_SPLIT) | I35: =I33*(1-T4_LP_SPLIT) | J35: =J33*(1-T4_LP_SPLIT) | ... CH35: =CH33*(1-T4_LP_SPLIT)
A36: Tier sum | B36: $ | C36: =C9+C20+C28+C33 | D36: =D9+D20+D28+D33 | E36: =E9+E20+E28+E33 | F36: =F9+F20+F28+F33 | G36: =G9+G20+G28+G33 | H36: =H9+H20+H28+H33 | I36: =I9+I20+I28+I33 | J36: =J9+J20+J28+J33 | ... CH36: =CH9+CH20+CH28+CH33
A37: LP distribution | B37: $ | C37: =C9+C29+C34 | D37: =D9+D29+D34 | E37: =E9+E29+E34 | F37: =F9+F29+F34 | G37: =G9+G29+G34 | H37: =H9+H29+H34 | I37: =I9+I29+I34 | J37: =J9+J29+J34 | ... CH37: =CH9+CH29+CH34
A38: GP distribution | B38: $ | C38: =C20+C30+C35 | D38: =D20+D30+D35 | E38: =E20+E30+E35 | F38: =F20+F30+F35 | G38: =G20+G30+G35 | H38: =H20+H30+H35 | I38: =I20+I30+I35 | J38: =J20+J30+J35 | ... CH38: =CH20+CH30+CH35
A39: Cumulative LP distributions | B39: $ | C39: =C37 | D39: =C39+D37 | E39: =D39+E37 | F39: =E39+F37 | G39: =F39+G37 | H39: =G39+H37 | I39: =H39+I37 | J39: =I39+J37 | K39: =J39+K37 | ... CH39: =CG39+CH37
A40: Audit tier gap | B40: $ | C40: =ABS(C36-C4) | D40: =ABS(D36-D4) | E40: =ABS(E36-E4) | F40: =ABS(F36-F4) | G40: =ABS(G36-G4) | H40: =ABS(H36-H4) | I40: =ABS(I36-I4) | J40: =ABS(J36-J4) | ... CH40: =ABS(CH36-CH4)
A41: Audit tier 2 before tier 1 | B41: count | C41: =IF(AND(C20>0.01,C8-MAX(C9,0)>0.01),1,0) | D41: =IF(AND(D20>0.01,D8-MAX(D9,0)>0.01),1,0) | E41: =IF(AND(E20>0.01,E8-MAX(E9,0)>0.01),1,0) | F41: =IF(AND(F20>0.01,F8-MAX(F9,0)>0.01),1,0) | G41: =IF(AND(G20>0.01,G8-MAX(G9,0)>0.01),1,0) | H41: =IF(AND(H20>0.01,H8-MAX(H9,0)>0.01),1,0) | I41: =IF(AND(I20>0.01,I8-MAX(I9,0)>0.01),1,0) | J41: =IF(AND(J20>0.01,J8-MAX(J9,0)>0.01),1,0) | ... CH41: =IF(AND(CH20>0.01,CH8-MAX(CH9,0)>0.01),1,0)
A42: Audit tier 3 before tier 2 | B42: count | C42: =IF(AND(C28>0.01,C22=0),1,0) | D42: =IF(AND(D28>0.01,D22=0),1,0) | E42: =IF(AND(E28>0.01,E22=0),1,0) | F42: =IF(AND(F28>0.01,F22=0),1,0) | G42: =IF(AND(G28>0.01,G22=0),1,0) | H42: =IF(AND(H28>0.01,H22=0),1,0) | I42: =IF(AND(I28>0.01,I22=0),1,0) | J42: =IF(AND(J28>0.01,J22=0),1,0) | ... CH42: =IF(AND(CH28>0.01,CH22=0),1,0)
A43: Audit tier 4 before gate | B43: count | C43: =IF(AND(ABS(C33)>0.01,C32=0),1,0) | D43: =IF(AND(ABS(D33)>0.01,D32=0),1,0) | E43: =IF(AND(ABS(E33)>0.01,E32=0),1,0) | F43: =IF(AND(ABS(F33)>0.01,F32=0),1,0) | G43: =IF(AND(ABS(G33)>0.01,G32=0),1,0) | H43: =IF(AND(ABS(H33)>0.01,H32=0),1,0) | I43: =IF(AND(ABS(I33)>0.01,I32=0),1,0) | J43: =IF(AND(ABS(J33)>0.01,J32=0),1,0) | ... CH43: =IF(AND(ABS(CH33)>0.01,CH32=0),1,0)

Sheet Returns
A1: Returns
A2: Month | B2: index | C2: =COLUMN()-2 | D2: =COLUMN()-2 | E2: =COLUMN()-2 | F2: =COLUMN()-2 | G2: =COLUMN()-2 | H2: =COLUMN()-2 | I2: =COLUMN()-2 | J2: =COLUMN()-2 | ... CH2: =COLUMN()-2
A3: Date | B3: month-end | C3: =EOMONTH(DATE(2026,1,1),C2-1) | D3: =EOMONTH(DATE(2026,1,1),D2-1) | E3: =EOMONTH(DATE(2026,1,1),E2-1) | F3: =EOMONTH(DATE(2026,1,1),F2-1) | G3: =EOMONTH(DATE(2026,1,1),G2-1) | H3: =EOMONTH(DATE(2026,1,1),H2-1) | I3: =EOMONTH(DATE(2026,1,1),I2-1) | J3: =EOMONTH(DATE(2026,1,1),J2-1) | ... CH3: =EOMONTH(DATE(2026,1,1),CH2-1)
A4: Project equity cash flow | B4: $ | C4: =-ConstructionDebt!C8+ProjectCF!C12 | D4: =-ConstructionDebt!D8+ProjectCF!D12 | E4: =-ConstructionDebt!E8+ProjectCF!E12 | F4: =-ConstructionDebt!F8+ProjectCF!F12 | G4: =-ConstructionDebt!G8+ProjectCF!G12 | H4: =-ConstructionDebt!H8+ProjectCF!H12 | I4: =-ConstructionDebt!I8+ProjectCF!I12 | J4: =-ConstructionDebt!J8+ProjectCF!J12 | ... CH4: =-ConstructionDebt!CH8+ProjectCF!CH12
A5: LP cash flow | B5: $ | C5: =IF(C2=1,-SourcesUses!$C$31,0)+Waterfall!C37 | D5: =IF(D2=1,-SourcesUses!$C$31,0)+Waterfall!D37 | E5: =IF(E2=1,-SourcesUses!$C$31,0)+Waterfall!E37 | F5: =IF(F2=1,-SourcesUses!$C$31,0)+Waterfall!F37 | G5: =IF(G2=1,-SourcesUses!$C$31,0)+Waterfall!G37 | H5: =IF(H2=1,-SourcesUses!$C$31,0)+Waterfall!H37 | I5: =IF(I2=1,-SourcesUses!$C$31,0)+Waterfall!I37 | J5: =IF(J2=1,-SourcesUses!$C$31,0)+Waterfall!J37 | ... CH5: =IF(CH2=1,-SourcesUses!$C$31,0)+Waterfall!CH37
A6: GP cash flow | B6: $ | C6: =IF(C2=1,-SourcesUses!$C$30,0)+Waterfall!C38 | D6: =IF(D2=1,-SourcesUses!$C$30,0)+Waterfall!D38 | E6: =IF(E2=1,-SourcesUses!$C$30,0)+Waterfall!E38 | F6: =IF(F2=1,-SourcesUses!$C$30,0)+Waterfall!F38 | G6: =IF(G2=1,-SourcesUses!$C$30,0)+Waterfall!G38 | H6: =IF(H2=1,-SourcesUses!$C$30,0)+Waterfall!H38 | I6: =IF(I2=1,-SourcesUses!$C$30,0)+Waterfall!I38 | J6: =IF(J2=1,-SourcesUses!$C$30,0)+Waterfall!J38 | ... CH6: =IF(CH2=1,-SourcesUses!$C$30,0)+Waterfall!CH38
A8: Project XIRR | B8: % | C8: =XIRR(C4:CH4,C3:CH3) | D8: XIRR is an output only. It does not trigger a tier.
A9: LP XIRR | B9: % | C9: =XIRR(C5:CH5,C3:CH3)
A10: GP XIRR | B10: % | C10: =XIRR(C6:CH6,C3:CH3)
A12: Project equity multiple | B12: x | C12: =SUM(ProjectCF!C12:CH12)/SourcesUses!$C$28
A13: LP equity multiple | B13: x | C13: =IF(SourcesUses!$C$31=0,0,SUM(Waterfall!C37:CH37)/SourcesUses!$C$31)
A14: GP equity multiple | B14: x | C14: =IF(SourcesUses!$C$30=0,0,SUM(Waterfall!C38:CH38)/SourcesUses!$C$30)
A16: LP distributions | B16: $ | C16: =SUM(Waterfall!C37:CH37)
A17: GP distributions | B17: $ | C17: =SUM(Waterfall!C38:CH38)
A18: Promote $ | B18: $ | C18: =C17-SourcesUses!$C$30 | D18: GP distributions minus GP contributed capital. GP capital is not a separate waterfall tier.

Sheet Checks
A1: Checks
A2: ID | B2: Identity | C2: Result
A3: MASTER | B3: All checks | C3: =AND(C5,C6,C7,C8,C9,C10,C11,C12,C13,C14,C15,C16)
A5: C1 | B5: Sources equal uses, and the uses component sum ties, within $1 | C5: =AND(ABS(SourcesUses!C33)<=1,ABS(SourcesUses!C25)<=1)
A6: C2 | B6: Every month, construction interest equals opening balance times (MAX(floor, SOFR)+spread)/12, within $0.01 | C6: =MAX(ConstructionDebt!C23:CH23)<=0.01
A7: C3 | B7: Every month, construction opening and closing balances are between 0 and commitment, within $1 | C7: =AND(MIN(ConstructionDebt!C12:CH12)>=-1,MIN(ConstructionDebt!C21:CH21)>=-1,MAX(ConstructionDebt!C12:CH12)<=SourcesUses!C22+1,MAX(ConstructionDebt!C21:CH21)<=SourcesUses!C22+1)
A8: C4 | B8: Permanent proceeds equal MIN(LTV size, DSCR size, debt-yield size), within $1 | C8: =ABS(PermanentDebt!C39-MIN(PermanentDebt!C35,PermanentDebt!C37,PermanentDebt!C38))<=1
A9: C5 | B9: Closings by type equal inventory, and gross sellout equals unit prices plus parking plus storage, within $1 | C9: =AND(ABS(SUM(CondoSellout!C4:CH4)-UNITS_STUDIO)<=1,ABS(SUM(CondoSellout!C5:CH5)-UNITS_1BR)<=1,ABS(SUM(CondoSellout!C6:CH6)-UNITS_2BR)<=1,ABS(SUM(CondoSellout!C7:CH7)-UNITS_3BR)<=1,ABS(SUM(CondoSellout!C8:CH8)-UNITS_PH)<=1,ABS(SUM(CondoSellout!C15:CH15)-(UNITS_STUDIO*SQFT_STUDIO*PPSF_STUDIO+UNITS_1BR*SQFT_1BR*PPSF_1BR+UNITS_2BR*SQFT_2BR*PPSF_2BR+UNITS_3BR*SQFT_3BR*PPSF_3BR+UNITS_PH*SQFT_PH*PPSF_PH+PARKING_SPACES*PARKING_PRICE+STORAGE_UNITS*STORAGE_PRICE))<=1)
A10: C6 | B10: Hotel value equals exit T12 NOI over hotel cap, and retail value equals exit T12 NOI over retail cap, within $1 | C10: =AND(ABS(HotelValuation!C7-HotelValuation!C6/HOTEL_CAP)<=1,ABS(RetailValuation!C7-RetailValuation!C6/RETAIL_CAP)<=1)
A11: C7 | B11: Every month, tier distributions equal distributable cash within $0.01, and retained cash at exit is 0 | C11: =AND(MAX(Waterfall!C40:CH40)<=0.01,ABS(INDEX(ProjectCF!C18:CH18,EXIT_M))<=0.01)
A12: C8 | B12: No tier 2 before tier 1 is paid, no tier 3 before tier 2 is complete, no tier 4 before the tier 3 gate | C12: =AND(SUM(Waterfall!C41:CH41)=0,SUM(Waterfall!C42:CH42)=0,SUM(Waterfall!C43:CH43)=0)
A13: C9 | B13: Equity contributions equal the equity requirement, within $1 | C13: =ABS(SUM(ConstructionDebt!C8:CH8)-SourcesUses!C28)<=1
A14: C10 | B14: Construction opening balance equals the prior opening balance plus draws minus repayments | C14: =MAX(ConstructionDebt!C24:CH24)<=0.01
A15: C11 | B15: Key calculated outputs are numbers, so those cells are not #REF!, #NAME?, #VALUE!, or #CYCLE! | C15: =AND(ISNUMBER(SourcesUses!C21),ISNUMBER(SourcesUses!C22),ISNUMBER(SourcesUses!C28),ISNUMBER(PermanentDebt!C39),ISNUMBER(HotelValuation!C7),ISNUMBER(RetailValuation!C7),ISNUMBER(SUM(ProjectCF!C12:CH12)),ISNUMBER(SUM(Waterfall!C9:CH9)))
A16: C12 | B16: Every SOFR source cell carries the ASSUMPTION placeholder label | C16: =COUNTIF(SOFR!D2:D85,"ASSUMPTION — placeholder forward; not a live Chatham quote. Paste Chatham forwards here.")=84
A18: Tolerances are $1 for balance and level checks and $0.01 for monthly flow checks.
